Workbook

Sheet Dashboard Executive
A1: PHARMACEUTICAL EVENTS OPERATIONS | EXECUTIVE DASHBOARD | FY 2025
A2: Generated: 24 June 2026 | Confidential – For Internal Use Only
A4: KEY PERFORMANCE INDICATORS
A5: TOTAL BUDGET | C5: TOTAL COMMITTED | E5: TOTAL ACTUAL | G5: CURRENT FORECAST | I5: SAVINGS / UNDERSPEND | K5: VARIANCE % | M5: TOTAL EVENTS | O5: ACTIVE EVENTS | Q5: COMPLETED
A6: =SUM('Budget Planning'!$J$2:$J$51) | C6: =SUM('Budget Planning'!$N$2:$N$51) | E6: =SUM('Budget Planning'!$O$2:$O$51) | G6: =SUM('Budget Planning'!$M$2:$M$51) | I6: =A6-G6 | K6: =IF(A6=0,0,I6/A6) | M6: =COUNTA('Event Master Database'!$A$2:$A$51) | O6: =COUNTIF('Event Master Database'!$L$2:$L$51,"Confirmed")+COUNTIF('Event Master Database'!$L$2:$L$51,"In Progress")+COUNTIF('Event Master Database'!$L$2:$L$51,"Planning") | Q6: =COUNTIF('Event Master Database'!$L$2:$L$51,"Completed")
A7: CANCELLED | C7: ON HOLD | E7: HIGH RISK SUPS | G7: OVERDUE INVOICES | I7: TOTAL POs | K7: FORECAST ACCURACY | M7: TOTAL SUPPLIERS | O7: AVG EVENT BUDGET | Q7: BUDGET UTILIZATION
A8: =COUNTIF('Event Master Database'!$L$2:$L$51,"Cancelled") | C8: =COUNTIF('Event Master Database'!$L$2:$L$51,"On Hold") | E8: =COUNTIF('Supplier Management'!$M$2:$M$149,"High") | G8: =COUNTIF('PO Tracking'!$N$2:$N$149,"Overdue") | I8: =COUNTA('PO Tracking'!$A$2:$A$149) | K8: =1-ABS(K6) | M8: =SUMPRODUCT(1/COUNTIF('Supplier Management'!$D$2:$D$149,'Supplier Management'!$D$2:$D$149)) | O8: =IF(M6=0,0,A6/M6) | Q8: =IF(A6=0,0,C6/A6)
A10: MONTHLY BUDGET VS FORECAST TREND (2025) | J10: BUDGET BY THERAPEUTIC AREA
A11: Month | B11: Budget (€) | C11: Forecast (€) | D11: Actual (€) | E11: Variance (€) | F11: Var % | G11: Events | H11: Status | J11: Therapeutic Area | K11: Budget (€) | L11: Committed (€) | M11: Utilization % | N11: Events
A12: Jan | B12: =SUMPRODUCT((MONTH('Budget Planning'!$H$2:$H$51)=1)*(YEAR('Budget Planning'!$H$2:$H$51)=2025)*'Budget Planning'!$J$2:$J$51) | C12: =SUMPRODUCT((MONTH('Budget Planning'!$H$2:$H$51)=1)*(YEAR('Budget Planning'!$H$2:$H$51)=2025)*'Budget Planning'!$M$2:$M$51) | D12: =SUMPRODUCT((MONTH('Budget Planning'!$H$2:$H$51)=1)*(YEAR('Budget Planning'!$H$2:$H$51)=2025)*'Budget Planning'!$O$2:$O$51) | E12: =B12-C12 | F12: =IF(B12=0,0,E12/B12) | G12: =SUMPRODUCT((MONTH('Budget Planning'!$H$2:$H$51)=1)*(YEAR('Budget Planning'!$H$2:$H$51)=2025)*1) | H12: =IF(F12<-0.05,"At Risk","On Track") | J12: Immunology | K12: =SUMIF('Budget Planning'!$E$2:$E$51,$J12,'Budget Planning'!$J$2:$J$51) | L12: =SUMIF('Budget Planning'!$E$2:$E$51,$J12,'Budget Planning'!$N$2:$N$51) | M12: =IF(K12=0,0,L12/K12) | N12: =COUNTIF('Budget Planning'!$E$2:$E$51,$J12)
A13: Feb | B13: =SUMPRODUCT((MONTH('Budget Planning'!$H$2:$H$51)=2)*(YEAR('Budget Planning'!$H$2:$H$51)=2025)*'Budget Planning'!$J$2:$J$51) | C13: =SUMPRODUCT((MONTH('Budget Planning'!$H$2:$H$51)=2)*(YEAR('Budget Planning'!$H$2:$H$51)=2025)*'Budget Planning'!$M$2:$M$51) | D13: =SUMPRODUCT((MONTH('Budget Planning'!$H$2:$H$51)=2)*(YEAR('Budget Planning'!$H$2:$H$51)=2025)*'Budget Planning'!$O$2:$O$51) | E13: =B13-C13 | F13: =IF(B13=0,0,E13/B13) | G13: =SUMPRODUCT((MONTH('Budget Planning'!$H$2:$H$51)=2)*(YEAR('Budget Planning'!$H$2:$H$51)=2025)*1) | H13: =IF(F13<-0.05,"At Risk","On Track") | J13: Neurology | K13: =SUMIF('Budget Planning'!$E$2:$E$51,$J13,'Budget Planning'!$J$2:$J$51) | L13: =SUMIF('Budget Planning'!$E$2:$E$51,$J13,'Budget Planning'!$N$2:$N$51) | M13: =IF(K13=0,0,L13/K13) | N13: =COUNTIF('Budget Planning'!$E$2:$E$51,$J13)
A14: Mar | B14: =SUMPRODUCT((MONTH('Budget Planning'!$H$2:$H$51)=3)*(YEAR('Budget Planning'!$H$2:$H$51)=2025)*'Budget Planning'!$J$2:$J$51) | C14: =SUMPRODUCT((MONTH('Budget Planning'!$H$2:$H$51)=3)*(YEAR('Budget Planning'!$H$2:$H$51)=2025)*'Budget Planning'!$M$2:$M$51) | D14: =SUMPRODUCT((MONTH('Budget Planning'!$H$2:$H$51)=3)*(YEAR('Budget Planning'!$H$2:$H$51)=2025)*'Budget Planning'!$O$2:$O$51) | E14: =B14-C14 | F14: =IF(B14=0,0,E14/B14) | G14: =SUMPRODUCT((MONTH('Budget Planning'!$H$2:$H$51)=3)*(YEAR('Budget Planning'!$H$2:$H$51)=2025)*1) | H14: =IF(F14<-0.05,"At Risk","On Track") | J14: Rare Diseases | K14: =SUMIF('Budget Planning'!$E$2:$E$51,$J14,'Budget Planning'!$J$2:$J$51) | L14: =SUMIF('Budget Planning'!$E$2:$E$51,$J14,'Budget Planning'!$N$2:$N$51) | M14: =IF(K14=0,0,L14/K14) | N14: =COUNTIF('Budget Planning'!$E$2:$E$51,$J14)
A15: Apr | B15: =SUMPRODUCT((MONTH('Budget Planning'!$H$2:$H$51)=4)*(YEAR('Budget Planning'!$H$2:$H$51)=2025)*'Budget Planning'!$J$2:$J$51) | C15: =SUMPRODUCT((MONTH('Budget Planning'!$H$2:$H$51)=4)*(YEAR('Budget Planning'!$H$2:$H$51)=2025)*'Budget Planning'!$M$2:$M$51) | D15: =SUMPRODUCT((MONTH('Budget Planning'!$H$2:$H$51)=4)*(YEAR('Budget Planning'!$H$2:$H$51)=2025)*'Budget Planning'!$O$2:$O$51) | E15: =B15-C15 | F15: =IF(B15=0,0,E15/B15) | G15: =SUMPRODUCT((MONTH('Budget Planning'!$H$2:$H$51)=4)*(YEAR('Budget Planning'!$H$2:$H$51)=2025)*1) | H15: =IF(F15<-0.05,"At Risk","On Track") | J15: Cardiology | K15: =SUMIF('Budget Planning'!$E$2:$E$51,$J15,'Budget Planning'!$J$2:$J$51) | L15: =SUMIF('Budget Planning'!$E$2:$E$51,$J15,'Budget Planning'!$N$2:$N$51) | M15: =IF(K15=0,0,L15/K15) | N15: =COUNTIF('Budget Planning'!$E$2:$E$51,$J15)
A16: May | B16: =SUMPRODUCT((MONTH('Budget Planning'!$H$2:$H$51)=5)*(YEAR('Budget Planning'!$H$2:$H$51)=2025)*'Budget Planning'!$J$2:$J$51) | C16: =SUMPRODUCT((MONTH('Budget Planning'!$H$2:$H$51)=5)*(YEAR('Budget Planning'!$H$2:$H$51)=2025)*'Budget Planning'!$M$2:$M$51) | D16: =SUMPRODUCT((MONTH('Budget Planning'!$H$2:$H$51)=5)*(YEAR('Budget Planning'!$H$2:$H$51)=2025)*'Budget Planning'!$O$2:$O$51) | E16: =B16-C16 | F16: =IF(B16=0,0,E16/B16) | G16: =SUMPRODUCT((MONTH('Budget Planning'!$H$2:$H$51)=5)*(YEAR('Budget Planning'!$H$2:$H$51)=2025)*1) | H16: =IF(F16<-0.05,"At Risk","On Track") | J16: Oncology | K16: =SUMIF('Budget Planning'!$E$2:$E$51,$J16,'Budget Planning'!$J$2:$J$51) | L16: =SUMIF('Budget Planning'!$E$2:$E$51,$J16,'Budget Planning'!$N$2:$N$51) | M16: =IF(K16=0,0,L16/K16) | N16: =COUNTIF('Budget Planning'!$E$2:$E$51,$J16)
A17: Jun | B17: =SUMPRODUCT((MONTH('Budget Planning'!$H$2:$H$51)=6)*(YEAR('Budget Planning'!$H$2:$H$51)=2025)*'Budget Planning'!$J$2:$J$51) | C17: =SUMPRODUCT((MONTH('Budget Planning'!$H$2:$H$51)=6)*(YEAR('Budget Planning'!$H$2:$H$51)=2025)*'Budget Planning'!$M$2:$M$51) | D17: =SUMPRODUCT((MONTH('Budget Planning'!$H$2:$H$51)=6)*(YEAR('Budget Planning'!$H$2:$H$51)=2025)*'Budget Planning'!$O$2:$O$51) | E17: =B17-C17 | F17: =IF(B17=0,0,E17/B17) | G17: =SUMPRODUCT((MONTH('Budget Planning'!$H$2:$H$51)=6)*(YEAR('Budget Planning'!$H$2:$H$51)=2025)*1) | H17: =IF(F17<-0.05,"At Risk","On Track") | J17: Infectious Diseases | K17: =SUMIF('Budget Planning'!$E$2:$E$51,$J17,'Budget Planning'!$J$2:$J$51) | L17: =SUMIF('Budget Planning'!$E$2:$E$51,$J17,'Budget Planning'!$N$2:$N$51) | M17: =IF(K17=0,0,L17/K17) | N17: =COUNTIF('Budget Planning'!$E$2:$E$51,$J17)
A18: Jul | B18: =SUMPRODUCT((MONTH('Budget Planning'!$H$2:$H$51)=7)*(YEAR('Budget Planning'!$H$2:$H$51)=2025)*'Budget Planning'!$J$2:$J$51) | C18: =SUMPRODUCT((MONTH('Budget Planning'!$H$2:$H$51)=7)*(YEAR('Budget Planning'!$H$2:$H$51)=2025)*'Budget Planning'!$M$2:$M$51) | D18: =SUMPRODUCT((MONTH('Budget Planning'!$H$2:$H$51)=7)*(YEAR('Budget Planning'!$H$2:$H$51)=2025)*'Budget Planning'!$O$2:$O$51) | E18: =B18-C18 | F18: =IF(B18=0,0,E18/B18) | G18: =SUMPRODUCT((MONTH('Budget Planning'!$H$2:$H$51)=7)*(YEAR('Budget Planning'!$H$2:$H$51)=2025)*1) | H18: =IF(F18<-0.05,"At Risk","On Track") | J18: Hematology | K18: =SUMIF('Budget Planning'!$E$2:$E$51,$J18,'Budget Planning'!$J$2:$J$51) | L18: =SUMIF('Budget Planning'!$E$2:$E$51,$J18,'Budget Planning'!$N$2:$N$51) | M18: =IF(K18=0,0,L18/K18) | N18: =COUNTIF('Budget Planning'!$E$2:$E$51,$J18)
A19: Aug | B19: =SUMPRODUCT((MONTH('Budget Planning'!$H$2:$H$51)=8)*(YEAR('Budget Planning'!$H$2:$H$51)=2025)*'Budget Planning'!$J$2:$J$51) | C19: =SUMPRODUCT((MONTH('Budget Planning'!$H$2:$H$51)=8)*(YEAR('Budget Planning'!$H$2:$H$51)=2025)*'Budget Planning'!$M$2:$M$51) | D19: =SUMPRODUCT((MONTH('Budget Planning'!$H$2:$H$51)=8)*(YEAR('Budget Planning'!$H$2:$H$51)=2025)*'Budget Planning'!$O$2:$O$51) | E19: =B19-C19 | F19: =IF(B19=0,0,E19/B19) | G19: =SUMPRODUCT((MONTH('Budget Planning'!$H$2:$H$51)=8)*(YEAR('Budget Planning'!$H$2:$H$51)=2025)*1) | H19: =IF(F19<-0.05,"At Risk","On Track") | J19: Gastroenterology | K19: =SUMIF('Budget Planning'!$E$2:$E$51,$J19,'Budget Planning'!$J$2:$J$51) | L19: =SUMIF('Budget Planning'!$E$2:$E$51,$J19,'Budget Planning'!$N$2:$N$51) | M19: =IF(K19=0,0,L19/K19) | N19: =COUNTIF('Budget Planning'!$E$2:$E$51,$J19)
A20: Sep | B20: =SUMPRODUCT((MONTH('Budget Planning'!$H$2:$H$51)=9)*(YEAR('Budget Planning'!$H$2:$H$51)=2025)*'Budget Planning'!$J$2:$J$51) | C20: =SUMPRODUCT((MONTH('Budget Planning'!$H$2:$H$51)=9)*(YEAR('Budget Planning'!$H$2:$H$51)=2025)*'Budget Planning'!$M$2:$M$51) | D20: =SUMPRODUCT((MONTH('Budget Planning'!$H$2:$H$51)=9)*(YEAR('Budget Planning'!$H$2:$H$51)=2025)*'Budget Planning'!$O$2:$O$51) | E20: =B20-C20 | F20: =IF(B20=0,0,E20/B20) | G20: =SUMPRODUCT((MONTH('Budget Planning'!$H$2:$H$51)=9)*(YEAR('Budget Planning'!$H$2:$H$51)=2025)*1) | H20: =IF(F20<-0.05,"At Risk","On Track")
A21: Oct | B21: =SUMPRODUCT((MONTH('Budget Planning'!$H$2:$H$51)=10)*(YEAR('Budget Planning'!$H$2:$H$51)=2025)*'Budget Planning'!$J$2:$J$51) | C21: =SUMPRODUCT((MONTH('Budget Planning'!$H$2:$H$51)=10)*(YEAR('Budget Planning'!$H$2:$H$51)=2025)*'Budget Planning'!$M$2:$M$51) | D21: =SUMPRODUCT((MONTH('Budget Planning'!$H$2:$H$51)=10)*(YEAR('Budget Planning'!$H$2:$H$51)=2025)*'Budget Planning'!$O$2:$O$51) | E21: =B21-C21 | F21: =IF(B21=0,0,E21/B21) | G21: =SUMPRODUCT((MONTH('Budget Planning'!$H$2:$H$51)=10)*(YEAR('Budget Planning'!$H$2:$H$51)=2025)*1) | H21: =IF(F21<-0.05,"At Risk","On Track")
A22: Nov | B22: =SUMPRODUCT((MONTH('Budget Planning'!$H$2:$H$51)=11)*(YEAR('Budget Planning'!$H$2:$H$51)=2025)*'Budget Planning'!$J$2:$J$51) | C22: =SUMPRODUCT((MONTH('Budget Planning'!$H$2:$H$51)=11)*(YEAR('Budget Planning'!$H$2:$H$51)=2025)*'Budget Planning'!$M$2:$M$51) | D22: =SUMPRODUCT((MONTH('Budget Planning'!$H$2:$H$51)=11)*(YEAR('Budget Planning'!$H$2:$H$51)=2025)*'Budget Planning'!$O$2:$O$51) | E22: =B22-C22 | F22: =IF(B22=0,0,E22/B22) | G22: =SUMPRODUCT((MONTH('Budget Planning'!$H$2:$H$51)=11)*(YEAR('Budget Planning'!$H$2:$H$51)=2025)*1) | H22: =IF(F22<-0.05,"At Risk","On Track")
A23: Dec | B23: =SUMPRODUCT((MONTH('Budget Planning'!$H$2:$H$51)=12)*(YEAR('Budget Planning'!$H$2:$H$51)=2025)*'Budget Planning'!$J$2:$J$51) | C23: =SUMPRODUCT((MONTH('Budget Planning'!$H$2:$H$51)=12)*(YEAR('Budget Planning'!$H$2:$H$51)=2025)*'Budget Planning'!$M$2:$M$51) | D23: =SUMPRODUCT((MONTH('Budget Planning'!$H$2:$H$51)=12)*(YEAR('Budget Planning'!$H$2:$H$51)=2025)*'Budget Planning'!$O$2:$O$51) | E23: =B23-C23 | F23: =IF(B23=0,0,E23/B23) | G23: =SUMPRODUCT((MONTH('Budget Planning'!$H$2:$H$51)=12)*(YEAR('Budget Planning'!$H$2:$H$51)=2025)*1) | H23: =IF(F23<-0.05,"At Risk","On Track")
A26: EVENT STATUS DISTRIBUTION | J26: TOP 8 SUPPLIERS BY COMMITTED SPEND
A27: Status | B27: Count | C27: % of Total | D27: Budget (€) | E27: Avg Budget (€) | J27: Supplier | K27: Category | L27: Committed (€) | M27: Share % | N27: Risk
A28: Completed | B28: =COUNTIF('Event Master Database'!$L$2:$L$51,$A28) | C28: =IF(SUM($B$28:$B$34)=0,0,B28/SUM($B$28:$B$34)) | D28: =SUMPRODUCT(('Event Master Database'!$L$2:$L$51=$A28)*'Budget Planning'!$J$2:$J$51) | E28: =IF(B28=0,0,D28/B28) | J28: TechEvent Systems | K28: Registration & Tech | L28: =SUMIF('Supplier Management'!$D$2:$D$149,$J28,'Supplier Management'!$I$2:$I$149) | M28: =IF(SUM('Supplier Management'!$I$2:$I$149)=0,0,L28/SUM('Supplier Management'!$I$2:$I$149)) | N28: High
A29: Confirmed | B29: =COUNTIF('Event Master Database'!$L$2:$L$51,$A29) | C29: =IF(SUM($B$28:$B$34)=0,0,B29/SUM($B$28:$B$34)) | D29: =SUMPRODUCT(('Event Master Database'!$L$2:$L$51=$A29)*'Budget Planning'!$J$2:$J$51) | E29: =IF(B29=0,0,D29/B29) | J29: Translingua Pro | K29: Translation & Interpretation | L29: =SUMIF('Supplier Management'!$D$2:$D$149,$J29,'Supplier Management'!$I$2:$I$149) | M29: =IF(SUM('Supplier Management'!$I$2:$I$149)=0,0,L29/SUM('Supplier Management'!$I$2:$I$149)) | N29: High
A30: Cancelled | B30: =COUNTIF('Event Master Database'!$L$2:$L$51,$A30) | C30: =IF(SUM($B$28:$B$34)=0,0,B30/SUM($B$28:$B$34)) | D30: =SUMPRODUCT(('Event Master Database'!$L$2:$L$51=$A30)*'Budget Planning'!$J$2:$J$51) | E30: =IF(B30=0,0,D30/B30) | J30: InterCongress PCO | K30: PCO / Event Agency | L30: =SUMIF('Supplier Management'!$D$2:$D$149,$J30,'Supplier Management'!$I$2:$I$149) | M30: =IF(SUM('Supplier Management'!$I$2:$I$149)=0,0,L30/SUM('Supplier Management'!$I$2:$I$149)) | N30: Medium
A31: In Progress | B31: =COUNTIF('Event Master Database'!$L$2:$L$51,$A31) | C31: =IF(SUM($B$28:$B$34)=0,0,B31/SUM($B$28:$B$34)) | D31: =SUMPRODUCT(('Event Master Database'!$L$2:$L$51=$A31)*'Budget Planning'!$J$2:$J$51) | E31: =IF(B31=0,0,D31/B31) | J31: AVIAWORLD Travel | K31: Travel & Air | L31: =SUMIF('Supplier Management'!$D$2:$D$149,$J31,'Supplier Management'!$I$2:$I$149) | M31: =IF(SUM('Supplier Management'!$I$2:$I$149)=0,0,L31/SUM('Supplier Management'!$I$2:$I$149)) | N31: High
A32: Planning | B32: =COUNTIF('Event Master Database'!$L$2:$L$51,$A32) | C32: =IF(SUM($B$28:$B$34)=0,0,B32/SUM($B$28:$B$34)) | D32: =SUMPRODUCT(('Event Master Database'!$L$2:$L$51=$A32)*'Budget Planning'!$J$2:$J$51) | E32: =IF(B32=0,0,D32/B32) | J32: Catering Excellence | K32: F&B / Catering | L32: =SUMIF('Supplier Management'!$D$2:$D$149,$J32,'Supplier Management'!$I$2:$I$149) | M32: =IF(SUM('Supplier Management'!$I$2:$I$149)=0,0,L32/SUM('Supplier Management'!$I$2:$I$149)) | N32: High
A33: Closed | B33: =COUNTIF('Event Master Database'!$L$2:$L$51,$A33) | C33: =IF(SUM($B$28:$B$34)=0,0,B33/SUM($B$28:$B$34)) | D33: =SUMPRODUCT(('Event Master Database'!$L$2:$L$51=$A33)*'Budget Planning'!$J$2:$J$51) | E33: =IF(B33=0,0,D33/B33) | J33: PharmaLogix | K33: Logistics & Transport | L33: =SUMIF('Supplier Management'!$D$2:$D$149,$J33,'Supplier Management'!$I$2:$I$149) | M33: =IF(SUM('Supplier Management'!$I$2:$I$149)=0,0,L33/SUM('Supplier Management'!$I$2:$I$149)) | N33: Medium
A34: On Hold | B34: =COUNTIF('Event Master Database'!$L$2:$L$51,$A34) | C34: =IF(SUM($B$28:$B$34)=0,0,B34/SUM($B$28:$B$34)) | D34: =SUMPRODUCT(('Event Master Database'!$L$2:$L$51=$A34)*'Budget Planning'!$J$2:$J$51) | E34: =IF(B34=0,0,D34/B34) | J34: HealthMarketing Group | K34: Marketing Agency | L34: =SUMIF('Supplier Management'!$D$2:$D$149,$J34,'Supplier Management'!$I$2:$I$149) | M34: =IF(SUM('Supplier Management'!$I$2:$I$149)=0,0,L34/SUM('Supplier Management'!$I$2:$I$149)) | N34: High
J35: Venue Masters EMEA | K35: Venue Sourcing | L35: =SUMIF('Supplier Management'!$D$2:$D$149,$J35,'Supplier Management'!$I$2:$I$149) | M35: =IF(SUM('Supplier Management'!$I$2:$I$149)=0,0,L35/SUM('Supplier Management'!$I$2:$I$149)) | N35: High

Sheet Event Master Database
A1: Event ID | B1: Event Name | C1: Therapeutic Area | D1: Product | E1: Business Unit | F1: Event Type | G1: Start Date | H1: End Date | I1: Duration (Days) | J1: City | K1: Country | L1: Status | M1: Responsible Owner | N1: Cost Center | O1: GL Account | P1: Created Date | Q1: Last Modified | R1: Notes
A2: EVT-2025-001 | B2: Cordavex Internal Meeting Vienna Apr 2025 | C2: Cardiology | D2: Cordavex | E2: BU Cardiovascular | F2: Internal Meeting | G2: 45772 | H2: 45773 | I2: 2 | J2: Vienna | K2: Austria | L2: Completed | M2: Maria Kowalski | N2: CC-1500 | O2: GL-6311 | P2: 45665 | Q2: 45685
A3: EVT-2025-002 | B3: Eplitazan Investigator Meeting Barcelona Jan 2025 | C3: Cardiology | D3: Eplitazan | E3: BU Cardiovascular | F3: Investigator Meeting | G3: 45673 | H3: 45674 | I3: 2 | J3: Barcelona | K3: Spain | L3: Confirmed | M3: Lena Schneider | N3: CC-8308 | O3: GL-6311 | P3: 45502 | Q3: 45522
A4: EVT-2025-003 | B4: Influximab Webinar Athens Apr 2025 | C4: Immunology | D4: Influximab | E4: BU Immunology | F4: Webinar | G4: 45770 | H4: 45772 | I4: 3 | J4: Athens | K4: Greece | L4: Completed | M4: Ana García | N4: CC-6730 | O4: GL-6312 | P4: 45690 | Q4: 45703
A5: EVT-2025-004 | B5: Cognivex Investigator Meeting Stockholm May 2025 | C5: Neurology | D5: Cognivex | E5: BU Neuroscience | F5: Investigator Meeting | G5: 45800 | H5: 45802 | I5: 3 | J5: Stockholm | K5: Sweden | L5: Confirmed | M5: Lucas Dupont | N5: CC-2480 | O5: GL-6312 | P5: 45737 | Q5: 45754
A6: EVT-2025-005 | B6: Hemaflex Launch Event Brussels Nov 2025 | C6: Hematology | D6: Hemaflex | E6: BU Oncology | F6: Launch Event | G6: 45967 | H6: 45969 | I6: 3 | J6: Brussels | K6: Belgium | L6: Cancelled | M6: Thomas Dubois | N6: CC-1813 | O6: GL-6311 | P6: 45798 | Q6: 45821
A7: EVT-2025-006 | B7: Miotrex Advisory Board Istanbul May 2025 | C7: Cardiology | D7: Miotrex | E7: BU Cardiovascular | F7: Advisory Board | G7: 45808 | H7: 45810 | I7: 3 | J7: Istanbul | K7: Turkey | L7: Completed | M7: Thomas Dubois | N7: CC-4511 | O7: GL-6311 | P7: 45666 | Q7: 45678
A8: EVT-2025-007 | B8: Bioflair Advisory Board Vienna Feb 2025 | C8: Immunology | D8: Bioflair | E8: BU Immunology | F8: Advisory Board | G8: 45709 | H8: 45711 | I8: 3 | J8: Vienna | K8: Austria | L8: In Progress | M8: Maria Kowalski | N8: CC-4387 | O8: GL-6312 | P8: 45566 | Q8: 45584
A9: EVT-2025-008 | B9: Axotrin Launch Event Amsterdam Dec 2025 | C9: Neurology | D9: Axotrin | E9: BU Neuroscience | F9: Launch Event | G9: 46001 | H9: 46003 | I9: 3 | J9: Amsterdam | K9: Netherlands | L9: Completed | M9: Maria Kowalski | N9: CC-9409 | O9: GL-6310 | P9: 45831 | Q9: 45860
A10: EVT-2025-009 | B10: Cognivex KOL Meeting Milan Aug 2025 | C10: Neurology | D10: Cognivex | E10: BU Neuroscience | F10: KOL Meeting | G10: 45894 | H10: 45896 | I10: 3 | J10: Milan | K10: Italy | L10: Confirmed | M10: Maria Kowalski | N10: CC-1145 | O10: GL-6315 | P10: 45718 | Q10: 45727
A11: EVT-2025-010 | B11: Influximab Launch Event Barcelona Apr 2025 | C11: Immunology | D11: Influximab | E11: BU Immunology | F11: Launch Event | G11: 45775 | H11: 45776 | I11: 2 | J11: Barcelona | K11: Spain | L11: Cancelled | M11: Emma Johansson | N11: CC-3837 | O11: GL-6320 | P11: 45613 | Q11: 45618
A12: EVT-2025-011 | B12: Influximab Launch Event Amsterdam Dec 2025 | C12: Immunology | D12: Influximab | E12: BU Immunology | F12: Launch Event | G12: 45993 | H12: 45995 | I12: 3 | J12: Amsterdam | K12: Netherlands | L12: Completed | M12: Maria Kowalski | N12: CC-4666 | O12: GL-6312 | P12: 45856 | Q12: 45886
A13: EVT-2025-012 | B13: Rarzolene KOL Meeting Istanbul Oct 2025 | C13: Rare Diseases | D13: Rarzolene | E13: BU Rare Diseases | F13: KOL Meeting | G13: 45933 | H13: 45935 | I13: 3 | J13: Istanbul | K13: Turkey | L13: Completed | M13: Emma Johansson | N13: CC-6004 | O13: GL-6312 | P13: 45819 | Q13: 45836
... A51: EVT-2025-050 | B51: Infectoban Launch Event Paris Jun 2025 | C51: Infectious Diseases | D51: Infectoban | E51: BU Infectious Diseases | F51: Launch Event | G51: 45811 | H51: 45813 | I51: 3 | J51: Paris | K51: France | L51: Completed | M51: Lucas Dupont | N51: CC-9745 | O51: GL-6311 | P51: 45658 | Q51: 45674

Sheet Budget Planning
A1: Event ID | B1: Event Name | C1: Cost Center | D1: GL Account | E1: Therapeutic Area | F1: Business Unit | G1: Event Type | H1: Start Date | I1: Initial Budget (€) | J1: Approved Budget (€) | K1: Forecast V1 (€) | L1: Forecast V2 (€) | M1: Current Forecast (€) | N1: Committed (€) | O1: Actual Spend (€) | P1: Remaining Budget (€) | Q1: Budget Variance (€) | R1: Variance % | S1: Forecast Version | T1: Budget Status | U1: Approval Date | V1: Approved By
A2: EVT-2025-001 | B2: Cordavex Internal Meeting Vienna Apr 2025 | C2: CC-3851 | D2: GL-6320 | E2: Cardiology | F2: BU Cardiovascular | G2: Internal Meeting | H2: 45772 | I2: 374223.86 | J2: 358929.72 | K2: 345551.97 | L2: 351166.88 | M2: =L2 | N2: 324184.5 | O2: 292801.94 | P2: =M2-N2 | Q2: =J2-M2 | R2: =IF(J2=0,0,Q2/J2) | S2: FV3 | T2: On Track | U2: 45723 | V2: Thomas Dubois
A3: EVT-2025-002 | B3: Eplitazan Investigator Meeting Barcelona Jan 2025 | C3: CC-4443 | D3: GL-6315 | E3: Cardiology | F3: BU Cardiovascular | G3: Investigator Meeting | H3: 45673 | I3: 306979.08 | J3: 311221.85 | K3: 308298.7 | L3: 327323.74 | M3: =L3 | N3: 208421.34 | O3: 0 | P3: =M3-N3 | Q3: =J3-M3 | R3: =IF(J3=0,0,Q3/J3) | S3: FV1 | T3: At Risk | U3: 45555 | V3: Maria Kowalski
A4: EVT-2025-003 | B4: Influximab Webinar Athens Apr 2025 | C4: CC-9375 | D4: GL-6315 | E4: Immunology | F4: BU Immunology | G4: Webinar | H4: 45770 | I4: 383021.57 | J4: 404911.93 | K4: 409230.78 | L4: 411460.03 | M4: =L4 | N4: 287529.79 | O4: 259549.74 | P4: =M4-N4 | Q4: =J4-M4 | R4: =IF(J4=0,0,Q4/J4) | S4: FV3 | T4: On Track | U4: 45660 | V4: David O'Brien
A5: EVT-2025-004 | B5: Cognivex Investigator Meeting Stockholm May 2025 | C5: CC-5649 | D5: GL-6320 | E5: Neurology | F5: BU Neuroscience | G5: Investigator Meeting | H5: 45800 | I5: 64571.98 | J5: 68365.4 | K5: 71509.06 | L5: 75152.86 | M5: =L5 | N5: 59857.96 | O5: 0 | P5: =M5-N5 | Q5: =J5-M5 | R5: =IF(J5=0,0,Q5/J5) | S5: FV1 | T5: At Risk | U5: 45732 | V5: Emma Johansson
A6: EVT-2025-005 | B6: Hemaflex Launch Event Brussels Nov 2025 | C6: CC-4848 | D6: GL-6325 | E6: Hematology | F6: BU Oncology | G6: Launch Event | H6: 45967 | I6: 237821.07 | J6: 245614.65 | K6: 248543.87 | L6: 243640.74 | M6: =L6 | N6: 226196.03 | O6: 0 | P6: =M6-N6 | Q6: =J6-M6 | R6: =IF(J6=0,0,Q6/J6) | S6: FV2 | T6: On Track | U6: 45853 | V6: Ana García
A7: EVT-2025-006 | B7: Miotrex Advisory Board Istanbul May 2025 | C7: CC-2193 | D7: GL-6315 | E7: Cardiology | F7: BU Cardiovascular | G7: Advisory Board | H7: 45808 | I7: 48734.25 | J7: 46886.44 | K7: 48323.8 | L7: 47657.36 | M7: =L7 | N7: 24819.77 | O7: 24700.16 | P7: =M7-N7 | Q7: =J7-M7 | R7: =IF(J7=0,0,Q7/J7) | S7: FV1 | T7: On Track | U7: 45694 | V7: Ana García
A8: EVT-2025-007 | B8: Bioflair Advisory Board Vienna Feb 2025 | C8: CC-4997 | D8: GL-6311 | E8: Immunology | F8: BU Immunology | G8: Advisory Board | H8: 45709 | I8: 419543.56 | J8: 412364.42 | K8: 417715.48 | L8: 414118.06 | M8: =L8 | N8: 336826.82 | O8: 285734.62 | P8: =M8-N8 | Q8: =J8-M8 | R8: =IF(J8=0,0,Q8/J8) | S8: FV3 | T8: On Track | U8: 45645 | V8: Lena Schneider
A9: EVT-2025-008 | B9: Axotrin Launch Event Amsterdam Dec 2025 | C9: CC-7965 | D9: GL-6311 | E9: Neurology | F9: BU Neuroscience | G9: Launch Event | H9: 46001 | I9: 329297.16 | J9: 339575.05 | K9: 322784.59 | L9: 339765.03 | M9: =L9 | N9: 287618.16 | O9: 210529.64 | P9: =M9-N9 | Q9: =J9-M9 | R9: =IF(J9=0,0,Q9/J9) | S9: FV3 | T9: On Track | U9: 45894 | V9: Sophie Müller
A10: EVT-2025-009 | B10: Cognivex KOL Meeting Milan Aug 2025 | C10: CC-5082 | D10: GL-6330 | E10: Neurology | F10: BU Neuroscience | G10: KOL Meeting | H10: 45894 | I10: 348758.55 | J10: 326151.09 | K10: 341087.7 | L10: 350288.66 | M10: =L10 | N10: 183060.25 | O10: 0 | P10: =M10-N10 | Q10: =J10-M10 | R10: =IF(J10=0,0,Q10/J10) | S10: FV3 | T10: At Risk | U10: 45847 | V10: Maria Kowalski
A11: EVT-2025-010 | B11: Influximab Launch Event Barcelona Apr 2025 | C11: CC-6198 | D11: GL-6330 | E11: Immunology | F11: BU Immunology | G11: Launch Event | H11: 45775 | I11: 144854.32 | J11: 133884.75 | K11: 128975.72 | L11: 131698.49 | M11: =L11 | N11: 97326.42 | O11: 0 | P11: =M11-N11 | Q11: =J11-M11 | R11: =IF(J11=0,0,Q11/J11) | S11: FV2 | T11: On Track | U11: 45732 | V11: James Wilson
A12: EVT-2025-011 | B12: Influximab Launch Event Amsterdam Dec 2025 | C12: CC-9976 | D12: GL-6315 | E12: Immunology | F12: BU Immunology | G12: Launch Event | H12: 45993 | I12: 237543.15 | J12: 256139.26 | K12: 259024.73 | L12: 271748.06 | M12: =L12 | N12: 197601.65 | O12: 187557.71 | P12: =M12-N12 | Q12: =J12-M12 | R12: =IF(J12=0,0,Q12/J12) | S12: FV3 | T12: At Risk | U12: 45884 | V12: Marco Bianchi
A13: EVT-2025-012 | B13: Rarzolene KOL Meeting Istanbul Oct 2025 | C13: CC-5543 | D13: GL-6330 | E13: Rare Diseases | F13: BU Rare Diseases | G13: KOL Meeting | H13: 45933 | I13: 450444.1 | J13: 486228.11 | K13: 498075.32 | L13: 509139.66 | M13: =L13 | N13: 313953.94 | O13: 243054.32 | P13: =M13-N13 | Q13: =J13-M13 | R13: =IF(J13=0,0,Q13/J13) | S13: FV1 | T13: On Track | U13: 45867 | V13: Emma Johansson
... A51: EVT-2025-050 | B51: Infectoban Launch Event Paris Jun 2025 | C51: CC-8381 | D51: GL-6325 | E51: Infectious Diseases | F51: BU Infectious Diseases | G51: Launch Event | H51: 45811 | I51: 210164.19 | J51: 216907.44 | K51: 209468.75 | L51: 207189.62 | M51: =L51 | N51: 110593.51 | O51: 77504.23 | P51: =M51-N51 | Q51: =J51-M51 | R51: =IF(J51=0,0,Q51/J51) | S51: FV2 | T51: On Track | U51: 45747 | V51: James Wilson
A53: TOTALS | I53: =SUM(I2:I51) | J53: =SUM(J2:J51) | K53: =SUM(K2:K51) | L53: =SUM(L2:L51) | M53: =SUM(M2:M51) | N53: =SUM(N2:N51) | O53: =SUM(O2:O51) | P53: =SUM(P2:P51) | Q53: =SUM(Q2:Q51)

Sheet Supplier Management
A1: Record ID | B1: Event ID | C1: Event Name | D1: Supplier Name | E1: Category | F1: Contract Status | G1: PO Number | H1: Invoice Number | I1: Amount (€) | J1: Currency | K1: Payment Status | L1: Due Date | M1: Risk Indicator | N1: Payment Terms (Days) | O1: Overdue Days | P1: Notes | Q1: Last Updated
A2: SUP-0001 | B2: EVT-2025-001 | C2: Cordavex Internal Meeting Vienna Apr 2025 | D2: Translingua Pro | E2: Translation & Interpretation | F2: Contract Sent | G2: PO-2025-1001 | H2: INV-01001 | I2: 56833.03 | J2: EUR | K2: Approved | L2: 45751 | M2: Low | N2: 90 | O2: 0 | Q2: 46175
A3: SUP-0002 | B3: EVT-2025-001 | C3: Cordavex Internal Meeting Vienna Apr 2025 | D3: Catering Excellence | E3: F&B / Catering | F3: Signed | G3: PO-2025-1002 | H3: INV-01002 | I3: 50754.52 | J3: EUR | K3: Approved | L3: 45744 | M3: Medium | N3: 90 | O3: 0 | Q3: 46172
A4: SUP-0003 | B4: EVT-2025-001 | C4: Cordavex Internal Meeting Vienna Apr 2025 | D4: AVIAWORLD Travel | E4: Travel & Air | F4: Negotiating | G4: PO-2025-1003 | I4: 19535.14 | J4: EUR | K4: Cancelled | L4: 45761 | M4: High | N4: 90 | O4: 0 | Q4: 46177
A5: SUP-0004 | B5: EVT-2025-001 | C5: Cordavex Internal Meeting Vienna Apr 2025 | D5: Prime Hospitality Group | E5: Hotel & Venue | F5: Active | G5: PO-2025-1004 | I5: 14941.98 | J5: EUR | K5: Cancelled | L5: 45756 | M5: Low | N5: 45 | O5: 0 | Q5: 46194
A6: SUP-0005 | B6: EVT-2025-001 | C6: Cordavex Internal Meeting Vienna Apr 2025 | D6: TechEvent Systems | E6: Registration & Tech | F6: Signed | G6: PO-2025-1005 | H6: INV-01005 | I6: 36253.97 | J6: EUR | K6: Disputed | L6: 45751 | M6: Medium | N6: 45 | O6: 0 | Q6: 46175
A7: SUP-0006 | B7: EVT-2025-002 | C7: Eplitazan Investigator Meeting Barcelona Jan 2025 | D7: PrintMed Solutions | E7: Print & Production | F7: Contract Sent | G7: PO-2025-1006 | H7: INV-01006 | I7: 48646.86 | J7: EUR | K7: Overdue | L7: 45653 | M7: Medium | N7: 30 | O7: 544 | Q7: 46167
A8: SUP-0007 | B8: EVT-2025-002 | C8: Eplitazan Investigator Meeting Barcelona Jan 2025 | D8: HealthMarketing Group | E8: Marketing Agency | F8: Active | G8: PO-2025-1007 | I8: 19856.1 | J8: EUR | K8: Overdue | L8: 45645 | M8: Medium | N8: 45 | O8: 552 | Q8: 46194
A9: SUP-0008 | B9: EVT-2025-002 | C9: Eplitazan Investigator Meeting Barcelona Jan 2025 | D9: Translingua Pro | E9: Translation & Interpretation | F9: RFP Sent | G9: PO-2025-1008 | H9: INV-01008 | I9: 79966.65 | J9: EUR | K9: Overdue | L9: 45645 | M9: Medium | N9: 90 | O9: 552 | Q9: 46168
A10: SUP-0009 | B10: EVT-2025-003 | C10: Influximab Webinar Athens Apr 2025 | D10: Translingua Pro | E10: Translation & Interpretation | F10: Closed | G10: PO-2025-1009 | H10: INV-01009 | I10: 73453.68 | J10: EUR | K10: Paid | L10: 45758 | M10: High | N10: 90 | O10: 0 | Q10: 46172
A11: SUP-0010 | B11: EVT-2025-003 | C11: Influximab Webinar Athens Apr 2025 | D11: PrintMed Solutions | E11: Print & Production | F11: Contract Sent | G11: PO-2025-1010 | H11: INV-01010 | I11: 77586.31 | J11: EUR | K11: Invoiced | L11: 45748 | M11: Low | N11: 90 | O11: 0 | Q11: 46192
A12: SUP-0011 | B12: EVT-2025-004 | C12: Cognivex Investigator Meeting Stockholm May 2025 | D12: TechEvent Systems | E12: Registration & Tech | F12: Terminated | G12: PO-2025-1011 | I12: 34108.32 | J12: EUR | K12: Paid | L12: 45778 | M12: Low | N12: 90 | O12: 0 | Q12: 46173
A13: SUP-0012 | B13: EVT-2025-005 | C13: Hemaflex Launch Event Brussels Nov 2025 | D13: AVIAWORLD Travel | E13: Travel & Air | F13: RFP Sent | G13: PO-2025-1012 | H13: INV-01012 | I13: 77674.41 | J13: EUR | K13: Cancelled | L13: 45948 | M13: Medium | N13: 60 | O13: 0 | Q13: 46178
A14: SUP-0013 | B14: EVT-2025-005 | C14: Hemaflex Launch Event Brussels Nov 2025 | D14: Translingua Pro | E14: Translation & Interpretation | F14: Contract Sent | G14: PO-2025-1013 | H14: INV-01013 | I14: 44322.3 | J14: EUR | K14: Overdue | L14: 45947 | M14: Low | N14: 30 | O14: 250 | Q14: 46170
A15: SUP-0014 | B15: EVT-2025-005 | C15: Hemaflex Launch Event Brussels Nov 2025 | D15: InterCongress PCO | E15: PCO / Event Agency | F15: Contract Sent | G15: PO-2025-1014 | H15: INV-01014 | I15: 40882.46 | J15: EUR | K15: Approved | L15: 45946 | M15: Medium | N15: 45 | O15: 0 | Q15: 46182
A16: SUP-0015 | B16: EVT-2025-005 | C16: Hemaflex Launch Event Brussels Nov 2025 | D16: PharmaLogix | E16: Logistics & Transport | F16: RFP Sent | G16: PO-2025-1015 | H16: INV-01015 | I16: 74358.48 | J16: EUR | K16: Paid | L16: 45946 | M16: Medium | N16: 90 | O16: 0 | Q16: 46194
A17: SUP-0016 | B17: EVT-2025-005 | C17: Hemaflex Launch Event Brussels Nov 2025 | D17: Catering Excellence | E17: F&B / Catering | F17: Active | G17: PO-2025-1016 | I17: 51141.74 | J17: EUR | K17: Invoiced | L17: 45953 | M17: Medium | N17: 90 | O17: 0 | Q17: 46183
A18: SUP-0017 | B18: EVT-2025-006 | C18: Miotrex Advisory Board Istanbul May 2025 | D18: PrintMed Solutions | E18: Print & Production | F18: Closed | G18: PO-2025-1017 | H18: INV-01017 | I18: 19526.65 | J18: EUR | K18: Pending | L18: 45798 | M18: Low | N18: 30 | O18: 0 | Q18: 46195
A19: SUP-0018 | B19: EVT-2025-007 | C19: Bioflair Advisory Board Vienna Feb 2025 | D19: Translingua Pro | E19: Translation & Interpretation | F19: Negotiating | G19: PO-2025-1018 | I19: 57022.11 | J19: EUR | K19: Paid | L19: 45689 | M19: Medium | N19: 60 | O19: 0 | Q19: 46177
A20: SUP-0019 | B20: EVT-2025-007 | C20: Bioflair Advisory Board Vienna Feb 2025 | D20: KOL Connect | E20: Speaker Management | F20: Closed | G20: PO-2025-1019 | H20: INV-01019 | I20: 13282.07 | J20: EUR | K20: Overdue | L20: 45696 | M20: High | N20: 60 | O20: 501 | Q20: 46197
A21: SUP-0020 | B21: EVT-2025-008 | C21: Axotrin Launch Event Amsterdam Dec 2025 | D21: TechEvent Systems | E21: Registration & Tech | F21: Active | G21: PO-2025-1020 | I21: 63620.48 | J21: EUR | K21: Cancelled | L21: 45981 | M21: Low | N21: 45 | O21: 0 | Q21: 46167
A22: SUP-0021 | B22: EVT-2025-008 | C22: Axotrin Launch Event Amsterdam Dec 2025 | D22: InterCongress PCO | E22: PCO / Event Agency | F22: Active | G22: PO-2025-1021 | I22: 2200.09 | J22: EUR | K22: Overdue | L22: 45971 | M22: Low | N22: 60 | O22: 226 | Q22: 46181
A23: SUP-0022 | B23: EVT-2025-009 | C23: Cognivex KOL Meeting Milan Aug 2025 | D23: TechEvent Systems | E23: Registration & Tech | F23: Terminated | G23: PO-2025-1022 | H23: INV-01022 | I23: 27930.32 | J23: EUR | K23: Invoiced | L23: 45870 | M23: Low | N23: 30 | O23: 0 | Q23: 46184
A24: SUP-0023 | B24: EVT-2025-009 | C24: Cognivex KOL Meeting Milan Aug 2025 | D24: MedAudio AV Solutions | E24: AV & Technology | F24: Terminated | G24: PO-2025-1023 | I24: 56404.88 | J24: EUR | K24: Cancelled | L24: 45869 | M24: Low | N24: 45 | O24: 0 | Q24: 46182
A25: SUP-0024 | B25: EVT-2025-009 | C25: Cognivex KOL Meeting Milan Aug 2025 | D25: Translingua Pro | E25: Translation & Interpretation | F25: Signed | G25: PO-2025-1024 | H25: INV-01024 | I25: 26817.75 | J25: EUR | K25: Cancelled | L25: 45872 | M25: Medium | N25: 60 | O25: 0 | Q25: 46176
A26: SUP-0025 | B26: EVT-2025-009 | C26: Cognivex KOL Meeting Milan Aug 2025 | D26: PrintMed Solutions | E26: Print & Production | F26: RFP Sent | G26: PO-2025-1025 | H26: INV-01025 | I26: 53767.73 | J26: EUR | K26: Paid | L26: 45867 | M26: High | N26: 90 | O26: 0 | Q26: 46193
A27: SUP-0026 | B27: EVT-2025-010 | C27: Influximab Launch Event Barcelona Apr 2025 | D27: PrintMed Solutions | E27: Print & Production | F27: RFP Sent | G27: PO-2025-1026 | H27: INV-01026 | I27: 9828.44 | J27: EUR | K27: Paid | L27: 45754 | M27: Low | N27: 30 | O27: 0 | Q27: 46197
A28: SUP-0027 | B28: EVT-2025-010 | C28: Influximab Launch Event Barcelona Apr 2025 | D28: DigitalPharma Studio | E28: Digital & Web | F28: Signed | G28: PO-2025-1027 | H28: INV-01027 | I28: 33978.33 | J28: EUR | K28: Pending | L28: 45748 | M28: High | N28: 45 | O28: 0 | Q28: 46181
A29: SUP-0028 | B29: EVT-2025-011 | C29: Influximab Launch Event Amsterdam Dec 2025 | D29: PharmaLogix | E29: Logistics & Transport | F29: Active | G29: PO-2025-1028 | H29: INV-01028 | I29: 8264.6 | J29: EUR | K29: Cancelled | L29: 45976 | M29: Medium | N29: 90 | O29: 0 | Q29: 46170
A30: SUP-0029 | B30: EVT-2025-011 | C30: Influximab Launch Event Amsterdam Dec 2025 | D30: DigitalPharma Studio | E30: Digital & Web | F30: Terminated | G30: PO-2025-1029 | H30: INV-01029 | I30: 26699.57 | J30: EUR | K30: Paid | L30: 45964 | M30: Medium | N30: 90 | O30: 0 | Q30: 46170
A31: SUP-0030 | B31: EVT-2025-011 | C31: Influximab Launch Event Amsterdam Dec 2025 | D31: KOL Connect | E31: Speaker Management | F31: Negotiating | G31: PO-2025-1030 | H31: INV-01030 | I31: 50161.84 | J31: EUR | K31: Invoiced | L31: 45979 | M31: Medium | N31: 45 | O31: 0 | Q31: 46195
A32: SUP-0031 | B32: EVT-2025-012 | C32: Rarzolene KOL Meeting Istanbul Oct 2025 | D32: MedComm Agency | E32: Medical Communication | F32: Negotiating | G32: PO-2025-1031 | H32: INV-01031 | I32: 61308.84 | J32: EUR | K32: Paid | L32: 45904 | M32: Medium | N32: 90 | O32: 0 | Q32: 46187
A33: SUP-0032 | B33: EVT-2025-013 | C33: Thrombovex KOL Meeting Berlin Sep 2025 | D33: HealthMarketing Group | E33: Marketing Agency | F33: Negotiating | G33: PO-2025-1032 | H33: INV-01032 | I33: 6377.3 | J33: EUR | K33: Approved | L33: 45900 | M33: Low | N33: 45 | O33: 0 | Q33: 46187
A34: SUP-0033 | B34: EVT-2025-013 | C34: Thrombovex KOL Meeting Berlin Sep 2025 | D34: AVIAWORLD Travel | E34: Travel & Air | F34: Active | G34: PO-2025-1033 | H34: INV-01033 | I34: 46142.39 | J34: EUR | K34: Pending | L34: 45906 | M34: Low | N34: 60 | O34: 0 | Q34: 46196
A35: SUP-0034 | B35: EVT-2025-013 | C35: Thrombovex KOL Meeting Berlin Sep 2025 | D35: TechEvent Systems | E35: Registration & Tech | F35: Negotiating | G35: PO-2025-1034 | H35: INV-01034 | I35: 50337.41 | J35: EUR | K35: Overdue | L35: 45904 | M35: Low | N35: 45 | O35: 293 | Q35: 46180
A36: SUP-0035 | B36: EVT-2025-014 | C36: Cognivex Speaker Program Athens Nov 2025 | D36: Translingua Pro | E36: Translation & Interpretation | F36: Contract Sent | G36: PO-2025-1035 | I36: 21915.48 | J36: EUR | K36: Paid | L36: 45956 | M36: Medium | N36: 90 | O36: 0 | Q36: 46185
A37: SUP-0036 | B37: EVT-2025-014 | C37: Cognivex Speaker Program Athens Nov 2025 | D37: Compliance Expert Ltd | E37: Compliance & Legal | F37: Contract Sent | G37: PO-2025-1036 | H37: INV-01036 | I37: 14322.1 | J37: EUR | K37: Overdue | L37: 45942 | M37: High | N37: 45 | O37: 255 | Q37: 46195
A38: SUP-0037 | B38: EVT-2025-015 | C38: Orphavex Congress Paris Dec 2025 | D38: KOL Connect | E38: Speaker Management | F38: Active | G38: PO-2025-1037 | I38: 32006.07 | J38: EUR | K38: Paid | L38: 45985 | M38: Low | N38: 90 | O38: 0 | Q38: 46183
A39: SUP-0038 | B39: EVT-2025-015 | C39: Orphavex Congress Paris Dec 2025 | D39: Catering Excellence | E39: F&B / Catering | F39: Closed | G39: PO-2025-1038 | H39: INV-01038 | I39: 25078.05 | J39: EUR | K39: Cancelled | L39: 45978 | M39: Low | N39: 90 | O39: 0 | Q39: 46195
A40: SUP-0039 | B40: EVT-2025-015 | C40: Orphavex Congress Paris Dec 2025 | D40: Translingua Pro | E40: Translation & Interpretation | F40: Active | G40: PO-2025-1039 | H40: INV-01039 | I40: 2631.64 | J40: EUR | K40: Pending | L40: 45979 | M40: Medium | N40: 90 | O40: 0 | Q40: 46183
A41: SUP-0040 | B41: EVT-2025-015 | C41: Orphavex Congress Paris Dec 2025 | D41: TechEvent Systems | E41: Registration & Tech | F41: Active | G41: PO-2025-1040 | H41: INV-01040 | I41: 66961.43 | J41: EUR | K41: Approved | L41: 45991 | M41: Medium | N41: 60 | O41: 0 | Q41: 46194
A42: SUP-0041 | B42: EVT-2025-016 | C42: Genetrix Speaker Program Warsaw Jan 2025 | D42: Prime Hospitality Group | E42: Hotel & Venue | F42: Terminated | G42: PO-2025-1041 | H42: INV-01041 | I42: 54865.63 | J42: EUR | K42: Disputed | L42: 45629 | M42: Medium | N42: 90 | O42: 0 | Q42: 46174
A43: SUP-0042 | B43: EVT-2025-016 | C43: Genetrix Speaker Program Warsaw Jan 2025 | D43: Compliance Expert Ltd | E43: Compliance & Legal | F43: Terminated | G43: PO-2025-1042 | I43: 9578.79 | J43: EUR | K43: Invoiced | L43: 45632 | M43: Medium | N43: 30 | O43: 0 | Q43: 46194
A44: SUP-0043 | B44: EVT-2025-016 | C44: Genetrix Speaker Program Warsaw Jan 2025 | D44: HealthMarketing Group | E44: Marketing Agency | F44: Contract Sent | G44: PO-2025-1043 | H44: INV-01043 | I44: 47206.76 | J44: EUR | K44: Invoiced | L44: 45629 | M44: Low | N44: 90 | O44: 0 | Q44: 46184
A45: SUP-0044 | B45: EVT-2025-017 | C45: Eplitazan Internal Meeting Budapest Nov 2025 | D45: MedAudio AV Solutions | E45: AV & Technology | F45: Negotiating | G45: PO-2025-1044 | H45: INV-01044 | I45: 30536.89 | J45: EUR | K45: Cancelled | L45: 45946 | M45: High | N45: 30 | O45: 0 | Q45: 46180
A46: SUP-0045 | B46: EVT-2025-017 | C46: Eplitazan Internal Meeting Budapest Nov 2025 | D46: Prime Hospitality Group | E46: Hotel & Venue | F46: Closed | G46: PO-2025-1045 | I46: 66325.81 | J46: EUR | K46: Invoiced | L46: 45947 | M46: High | N46: 30 | O46: 0 | Q46: 46171
A47: SUP-0046 | B47: EVT-2025-017 | C47: Eplitazan Internal Meeting Budapest Nov 2025 | D47: HealthMarketing Group | E47: Marketing Agency | F47: Terminated | G47: PO-2025-1046 | H47: INV-01046 | I47: 64730.14 | J47: EUR | K47: Approved | L47: 45948 | M47: High | N47: 30 | O47: 0 | Q47: 46172
A48: SUP-0047 | B48: EVT-2025-017 | C48: Eplitazan Internal Meeting Budapest Nov 2025 | D48: PrintMed Solutions | E48: Print & Production | F48: Terminated | G48: PO-2025-1047 | H48: INV-01047 | I48: 69090.97 | J48: EUR | K48: Paid | L48: 45939 | M48: Medium | N48: 60 | O48: 0 | Q48: 46169
A49: SUP-0048 | B49: EVT-2025-018 | C49: Caprexosin Launch Event Prague Jan 2025 | D49: PharmaLogix | E49: Logistics & Transport | F49: Contract Sent | G49: PO-2025-1048 | I49: 11639.92 | J49: EUR | K49: Disputed | L49: 45649 | M49: Medium | N49: 45 | O49: 0 | Q49: 46177
A50: SUP-0049 | B50: EVT-2025-018 | C50: Caprexosin Launch Event Prague Jan 2025 | D50: InterCongress PCO | E50: PCO / Event Agency | F50: Signed | G50: PO-2025-1049 | H50: INV-01049 | I50: 66148.55 | J50: EUR | K50: Approved | L50: 45649 | M50: Low | N50: 90 | O50: 0 | Q50: 46167
A51: SUP-0050 | B51: EVT-2025-018 | C51: Caprexosin Launch Event Prague Jan 2025 | D51: Venue Masters EMEA | E51: Venue Sourcing | F51: Negotiating | G51: PO-2025-1050 | I51: 70970.32 | J51: EUR | K51: Overdue | L51: 45643 | M51: Low | N51: 60 | O51: 554 | Q51: 46186
A52: SUP-0051 | B52: EVT-2025-018 | C52: Caprexosin Launch Event Prague Jan 2025 | D52: MedComm Agency | E52: Medical Communication | F52: Closed | G52: PO-2025-1051 | H52: INV-01051 | I52: 51561.51 | J52: EUR | K52: Invoiced | L52: 45646 | M52: High | N52: 30 | O52: 0 | Q52: 46171
A53: SUP-0052 | B53: EVT-2025-018 | C53: Caprexosin Launch Event Prague Jan 2025 | D53: AVIAWORLD Travel | E53: Travel & Air | F53: RFP Sent | G53: PO-2025-1052 | H53: INV-01052 | I53: 12902.61 | J53: EUR | K53: Paid | L53: 45659 | M53: Low | N53: 45 | O53: 0 | Q53: 46170
A54: SUP-0053 | B54: EVT-2025-019 | C54: Influximab Advisory Board London Sep 2025 | D54: Prime Hospitality Group | E54: Hotel & Venue | F54: Closed | G54: PO-2025-1053 | H54: INV-01053 | I54: 12581.8 | J54: EUR | K54: Disputed | L54: 45885 | M54: Low | N54: 90 | O54: 0 | Q54: 46187
A55: SUP-0054 | B55: EVT-2025-020 | C55: Cognivex Symposium Istanbul Mar 2025 | D55: MedComm Agency | E55: Medical Communication | F55: RFP Sent | G55: PO-2025-1054 | H55: INV-01054 | I55: 53083.91 | J55: EUR | K55: Invoiced | L55: 45720 | M55: Medium | N55: 90 | O55: 0 | Q55: 46175
A56: SUP-0055 | B56: EVT-2025-020 | C56: Cognivex Symposium Istanbul Mar 2025 | D56: DigitalPharma Studio | E56: Digital & Web | F56: Contract Sent | G56: PO-2025-1055 | H56: INV-01055 | I56: 18947.04 | J56: EUR | K56: Cancelled | L56: 45721 | M56: High | N56: 60 | O56: 0 | Q56: 46175
A57: SUP-0056 | B57: EVT-2025-020 | C57: Cognivex Symposium Istanbul Mar 2025 | D57: KOL Connect | E57: Speaker Management | F57: Contract Sent | G57: PO-2025-1056 | I57: 55483.06 | J57: EUR | K57: Disputed | L57: 45718 | M57: High | N57: 90 | O57: 0 | Q57: 46194
A58: SUP-0057 | B58: EVT-2025-020 | C58: Cognivex Symposium Istanbul Mar 2025 | D58: Venue Masters EMEA | E58: Venue Sourcing | F58: Signed | G58: PO-2025-1057 | I58: 23518.75 | J58: EUR | K58: Cancelled | L58: 45732 | M58: High | N58: 30 | O58: 0 | Q58: 46173
A59: SUP-0058 | B59: EVT-2025-020 | C59: Cognivex Symposium Istanbul Mar 2025 | D59: MedAudio AV Solutions | E59: AV & Technology | F59: RFP Sent | G59: PO-2025-1058 | I59: 18544.25 | J59: EUR | K59: Pending | L59: 45715 | M59: Low | N59: 45 | O59: 0 | Q59: 46197
A60: SUP-0059 | B60: EVT-2025-021 | C60: Influximab KOL Meeting Copenhagen Jul 2025 | D60: Prime Hospitality Group | E60: Hotel & Venue | F60: Terminated | G60: PO-2025-1059 | H60: INV-01059 | I60: 7351.59 | J60: EUR | K60: Approved | L60: 45838 | M60: Low | N60: 60 | O60: 0 | Q60: 46186
A61: SUP-0060 | B61: EVT-2025-021 | C61: Influximab KOL Meeting Copenhagen Jul 2025 | D61: MedAudio AV Solutions | E61: AV & Technology | F61: RFP Sent | G61: PO-2025-1060 | H61: INV-01060 | I61: 27627.65 | J61: EUR | K61: Overdue | L61: 45851 | M61: Medium | N61: 60 | O61: 346 | Q61: 46180
A62: SUP-0061 | B62: EVT-2025-021 | C62: Influximab KOL Meeting Copenhagen Jul 2025 | D62: Venue Masters EMEA | E62: Venue Sourcing | F62: Negotiating | G62: PO-2025-1061 | I62: 78754.19 | J62: EUR | K62: Cancelled | L62: 45851 | M62: Low | N62: 60 | O62: 0 | Q62: 46175
A63: SUP-0062 | B63: EVT-2025-022 | C63: Imunexal Advisory Board Stockholm Jan 2025 | D63: Compliance Expert Ltd | E63: Compliance & Legal | F63: Active | G63: PO-2025-1062 | H63: INV-01062 | I63: 12280.65 | J63: EUR | K63: Approved | L63: 45650 | M63: Medium | N63: 30 | O63: 0 | Q63: 46196
A64: SUP-0063 | B64: EVT-2025-023 | C64: Nexolimab Advisory Board Barcelona Jun 2025 | D64: AVIAWORLD Travel | E64: Travel & Air | F64: Signed | G64: PO-2025-1063 | I64: 59854.01 | J64: EUR | K64: Pending | L64: 45804 | M64: Low | N64: 45 | O64: 0 | Q64: 46182
A65: SUP-0064 | B65: EVT-2025-023 | C65: Nexolimab Advisory Board Barcelona Jun 2025 | D65: MedAudio AV Solutions | E65: AV & Technology | F65: Negotiating | G65: PO-2025-1064 | H65: INV-01064 | I65: 30239.04 | J65: EUR | K65: Overdue | L65: 45802 | M65: Low | N65: 45 | O65: 395 | Q65: 46171
A66: SUP-0065 | B66: EVT-2025-023 | C66: Nexolimab Advisory Board Barcelona Jun 2025 | D66: Catering Excellence | E66: F&B / Catering | F66: Closed | G66: PO-2025-1065 | H66: INV-01065 | I66: 5382.47 | J66: EUR | K66: Paid | L66: 45799 | M66: Low | N66: 90 | O66: 0 | Q66: 46194
A67: SUP-0066 | B67: EVT-2025-024 | C67: Influximab Speaker Program Dublin Oct 2025 | D67: AVIAWORLD Travel | E67: Travel & Air | F67: Closed | G67: PO-2025-1066 | H67: INV-01066 | I67: 68089.29 | J67: EUR | K67: Paid | L67: 45933 | M67: Medium | N67: 60 | O67: 0 | Q67: 46178
A68: SUP-0067 | B68: EVT-2025-025 | C68: Imunexal Advisory Board Athens Jul 2025 | D68: InterCongress PCO | E68: PCO / Event Agency | F68: Closed | G68: PO-2025-1067 | I68: 11842.94 | J68: EUR | K68: Overdue | L68: 45813 | M68: Medium | N68: 45 | O68: 384 | Q68: 46191
A69: SUP-0068 | B69: EVT-2025-025 | C69: Imunexal Advisory Board Athens Jul 2025 | D69: HealthMarketing Group | E69: Marketing Agency | F69: Active | G69: PO-2025-1068 | H69: INV-01068 | I69: 79580.96 | J69: EUR | K69: Overdue | L69: 45816 | M69: Low | N69: 30 | O69: 381 | Q69: 46168
A70: SUP-0069 | B70: EVT-2025-025 | C70: Imunexal Advisory Board Athens Jul 2025 | D70: PharmaLogix | E70: Logistics & Transport | F70: Terminated | G70: PO-2025-1069 | H70: INV-01069 | I70: 63861.5 | J70: EUR | K70: Disputed | L70: 45829 | M70: Medium | N70: 90 | O70: 0 | Q70: 46191
A71: SUP-0070 | B71: EVT-2025-025 | C71: Imunexal Advisory Board Athens Jul 2025 | D71: DigitalPharma Studio | E71: Digital & Web | F71: Signed | G71: PO-2025-1070 | H71: INV-01070 | I71: 69508.4 | J71: EUR | K71: Approved | L71: 45819 | M71: Low | N71: 90 | O71: 0 | Q71: 46171
A72: SUP-0071 | B72: EVT-2025-026 | C72: Cordavex Investigator Meeting Stockholm Feb 2025 | D72: TechEvent Systems | E72: Registration & Tech | F72: Contract Sent | G72: PO-2025-1071 | H72: INV-01071 | I72: 9416.7 | J72: EUR | K72: Invoiced | L72: 45693 | M72: Low | N72: 45 | O72: 0 | Q72: 46175
A73: SUP-0072 | B73: EVT-2025-026 | C73: Cordavex Investigator Meeting Stockholm Feb 2025 | D73: Translingua Pro | E73: Translation & Interpretation | F73: RFP Sent | G73: PO-2025-1072 | H73: INV-01072 | I73: 55572.04 | J73: EUR | K73: Cancelled | L73: 45691 | M73: Low | N73: 60 | O73: 0 | Q73: 46194
A74: SUP-0073 | B74: EVT-2025-026 | C74: Cordavex Investigator Meeting Stockholm Feb 2025 | D74: MedComm Agency | E74: Medical Communication | F74: Active | G74: PO-2025-1073 | I74: 9532.03 | J74: EUR | K74: Approved | L74: 45683 | M74: Low | N74: 90 | O74: 0 | Q74: 46196
A75: SUP-0074 | B75: EVT-2025-027 | C75: Hemaflex Internal Meeting Warsaw May 2025 | D75: DigitalPharma Studio | E75: Digital & Web | F75: Terminated | G75: PO-2025-1074 | H75: INV-01074 | I75: 45811.3 | J75: EUR | K75: Invoiced | L75: 45757 | M75: Low | N75: 30 | O75: 0 | Q75: 46173
A76: SUP-0075 | B76: EVT-2025-028 | C76: Nexolimab KOL Meeting Milan Jul 2025 | D76: TechEvent Systems | E76: Registration & Tech | F76: Closed | G76: PO-2025-1075 | H76: INV-01075 | I76: 29428.4 | J76: EUR | K76: Approved | L76: 45841 | M76: Low | N76: 90 | O76: 0 | Q76: 46183
A77: SUP-0076 | B77: EVT-2025-028 | C77: Nexolimab KOL Meeting Milan Jul 2025 | D77: KOL Connect | E77: Speaker Management | F77: RFP Sent | G77: PO-2025-1076 | H77: INV-01076 | I77: 68087.44 | J77: EUR | K77: Invoiced | L77: 45848 | M77: Medium | N77: 45 | O77: 0 | Q77: 46167
A78: SUP-0077 | B78: EVT-2025-028 | C78: Nexolimab KOL Meeting Milan Jul 2025 | D78: AVIAWORLD Travel | E78: Travel & Air | F78: Terminated | G78: PO-2025-1077 | H78: INV-01077 | I78: 46779.8 | J78: EUR | K78: Cancelled | L78: 45846 | M78: Medium | N78: 90 | O78: 0 | Q78: 46197
A79: SUP-0078 | B79: EVT-2025-028 | C79: Nexolimab KOL Meeting Milan Jul 2025 | D79: Catering Excellence | E79: F&B / Catering | F79: Terminated | G79: PO-2025-1078 | H79: INV-01078 | I79: 54648.18 | J79: EUR | K79: Disputed | L79: 45842 | M79: Low | N79: 30 | O79: 0 | Q79: 46180
A80: SUP-0079 | B80: EVT-2025-029 | C80: Axotrin Congress Lisbon May 2025 | D80: AVIAWORLD Travel | E80: Travel & Air | F80: Terminated | G80: PO-2025-1079 | H80: INV-01079 | I80: 26100.81 | J80: EUR | K80: Approved | L80: 45776 | M80: Low | N80: 90 | O80: 0 | Q80: 46171
A81: SUP-0080 | B81: EVT-2025-029 | C81: Axotrin Congress Lisbon May 2025 | D81: MedAudio AV Solutions | E81: AV & Technology | F81: RFP Sent | G81: PO-2025-1080 | I81: 53272.88 | J81: EUR | K81: Disputed | L81: 45784 | M81: Low | N81: 90 | O81: 0 | Q81: 46168
A82: SUP-0081 | B82: EVT-2025-029 | C82: Axotrin Congress Lisbon May 2025 | D82: Catering Excellence | E82: F&B / Catering | F82: Negotiating | G82: PO-2025-1081 | I82: 43377.65 | J82: EUR | K82: Invoiced | L82: 45774 | M82: Low | N82: 45 | O82: 0 | Q82: 46175
A83: SUP-0082 | B83: EVT-2025-030 | C83: Gastroven KOL Meeting Copenhagen Apr 2025 | D83: Catering Excellence | E83: F&B / Catering | F83: Negotiating | G83: PO-2025-1082 | H83: INV-01082 | I83: 46272.3 | J83: EUR | K83: Approved | L83: 45760 | M83: Medium | N83: 45 | O83: 0 | Q83: 46174
A84: SUP-0083 | B84: EVT-2025-030 | C84: Gastroven KOL Meeting Copenhagen Apr 2025 | D84: KOL Connect | E84: Speaker Management | F84: Signed | G84: PO-2025-1083 | H84: INV-01083 | I84: 5881.47 | J84: EUR | K84: Disputed | L84: 45760 | M84: Low | N84: 45 | O84: 0 | Q84: 46194
A85: SUP-0084 | B85: EVT-2025-030 | C85: Gastroven KOL Meeting Copenhagen Apr 2025 | D85: PharmaLogix | E85: Logistics & Transport | F85: RFP Sent | G85: PO-2025-1084 | H85: INV-01084 | I85: 36479.45 | J85: EUR | K85: Overdue | L85: 45754 | M85: Low | N85: 90 | O85: 443 | Q85: 46176
A86: SUP-0085 | B86: EVT-2025-031 | C86: Antivex Congress Dublin Sep 2025 | D86: MedComm Agency | E86: Medical Communication | F86: Negotiating | G86: PO-2025-1085 | H86: INV-01085 | I86: 48264.47 | J86: EUR | K86: Pending | L86: 45879 | M86: Medium | N86: 60 | O86: 0 | Q86: 46181
A87: SUP-0086 | B87: EVT-2025-031 | C87: Antivex Congress Dublin Sep 2025 | D87: InterCongress PCO | E87: PCO / Event Agency | F87: Terminated | G87: PO-2025-1086 | H87: INV-01086 | I87: 48747.35 | J87: EUR | K87: Approved | L87: 45895 | M87: Low | N87: 90 | O87: 0 | Q87: 46184
A88: SUP-0087 | B88: EVT-2025-031 | C88: Antivex Congress Dublin Sep 2025 | D88: Catering Excellence | E88: F&B / Catering | F88: Closed | G88: PO-2025-1087 | I88: 21930.52 | J88: EUR | K88: Paid | L88: 45885 | M88: Low | N88: 45 | O88: 0 | Q88: 46189
A89: SUP-0088 | B89: EVT-2025-032 | C89: Cordavex Advisory Board Helsinki Feb 2025 | D89: MedAudio AV Solutions | E89: AV & Technology | F89: Signed | G89: PO-2025-1088 | H89: INV-01088 | I89: 41020.46 | J89: EUR | K89: Pending | L89: 45664 | M89: Medium | N89: 90 | O89: 0 | Q89: 46167
A90: SUP-0089 | B90: EVT-2025-032 | C90: Cordavex Advisory Board Helsinki Feb 2025 | D90: HealthMarketing Group | E90: Marketing Agency | F90: Terminated | G90: PO-2025-1089 | H90: INV-01089 | I90: 5299.58 | J90: EUR | K90: Pending | L90: 45685 | M90: Low | N90: 60 | O90: 0 | Q90: 46188
A91: SUP-0090 | B91: EVT-2025-032 | C91: Cordavex Advisory Board Helsinki Feb 2025 | D91: MedComm Agency | E91: Medical Communication | F91: Contract Sent | G91: PO-2025-1090 | H91: INV-01090 | I91: 35484.17 | J91: EUR | K91: Paid | L91: 45673 | M91: Medium | N91: 90 | O91: 0 | Q91: 46172
A92: SUP-0091 | B92: EVT-2025-032 | C92: Cordavex Advisory Board Helsinki Feb 2025 | D92: PrintMed Solutions | E92: Print & Production | F92: Signed | G92: PO-2025-1091 | I92: 3626.81 | J92: EUR | K92: Overdue | L92: 45675 | M92: Low | N92: 45 | O92: 522 | Q92: 46193
A93: SUP-0092 | B93: EVT-2025-033 | C93: Caprexosin Advisory Board Athens Dec 2025 | D93: InterCongress PCO | E93: PCO / Event Agency | F93: Contract Sent | G93: PO-2025-1092 | I93: 47931.96 | J93: EUR | K93: Cancelled | L93: 45971 | M93: Low | N93: 90 | O93: 0 | Q93: 46178
A94: SUP-0093 | B94: EVT-2025-033 | C94: Caprexosin Advisory Board Athens Dec 2025 | D94: MedComm Agency | E94: Medical Communication | F94: RFP Sent | G94: PO-2025-1093 | H94: INV-01093 | I94: 19282.62 | J94: EUR | K94: Disputed | L94: 45982 | M94: Low | N94: 60 | O94: 0 | Q94: 46171
A95: SUP-0094 | B95: EVT-2025-033 | C95: Caprexosin Advisory Board Athens Dec 2025 | D95: HealthMarketing Group | E95: Marketing Agency | F95: Closed | G95: PO-2025-1094 | H95: INV-01094 | I95: 17124.49 | J95: EUR | K95: Cancelled | L95: 45976 | M95: Low | N95: 60 | O95: 0 | Q95: 46175
A96: SUP-0095 | B96: EVT-2025-034 | C96: Antivex Internal Meeting Lisbon Mar 2025 | D96: Prime Hospitality Group | E96: Hotel & Venue | F96: Closed | G96: PO-2025-1095 | I96: 17387.2 | J96: EUR | K96: Cancelled | L96: 45699 | M96: Low | N96: 45 | O96: 0 | Q96: 46191
A97: SUP-0096 | B97: EVT-2025-034 | C97: Antivex Internal Meeting Lisbon Mar 2025 | D97: InterCongress PCO | E97: PCO / Event Agency | F97: Active | G97: PO-2025-1096 | I97: 76200.79 | J97: EUR | K97: Cancelled | L97: 45698 | M97: Low | N97: 45 | O97: 0 | Q97: 46178
A98: SUP-0097 | B98: EVT-2025-035 | C98: Cordavex Webinar Amsterdam Sep 2025 | D98: Translingua Pro | E98: Translation & Interpretation | F98: RFP Sent | G98: PO-2025-1097 | H98: INV-01097 | I98: 27210.24 | J98: EUR | K98: Paid | L98: 45890 | M98: Low | N98: 60 | O98: 0 | Q98: 46176
A99: SUP-0098 | B99: EVT-2025-035 | C99: Cordavex Webinar Amsterdam Sep 2025 | D99: Compliance Expert Ltd | E99: Compliance & Legal | F99: Active | G99: PO-2025-1098 | H99: INV-01098 | I99: 51248.04 | J99: EUR | K99: Invoiced | L99: 45902 | M99: Low | N99: 60 | O99: 0 | Q99: 46168
A100: SUP-0099 | B100: EVT-2025-035 | C100: Cordavex Webinar Amsterdam Sep 2025 | D100: DigitalPharma Studio | E100: Digital & Web | F100: Contract Sent | G100: PO-2025-1099 | I100: 38015.91 | J100: EUR | K100: Cancelled | L100: 45909 | M100: Low | N100: 45 | O100: 0 | Q100: 46175
...

Sheet Cost Control
A1: Record ID | B1: Event ID | C1: Event Name | D1: Therapeutic Area | E1: Business Unit | F1: Cost Category | G1: Month | H1: Quarter | I1: Budgeted (€) | J1: Committed (€) | K1: Actual (€) | L1: Variance (€) | M1: Variance % | N1: Absorption % | O1: Over/Under | P1: Status
A2: CC-00001 | B2: EVT-2025-001 | C2: Cordavex Internal Meeting Vienna Apr 2025 | D2: Cardiology | E2: BU Cardiovascular | F2: Airfare | G2: Apr-2025 | H2: Q2 2025 | I2: 35116.69 | J2: 25963.35 | K2: 25655.84 | L2: =I2-J2 | M2: =IF(I2=0,0,ROUND((I2-J2)/I2,4)) | N2: =IF(I2=0,0,J2/I2) | O2: =IF(L2>=0,"Under","Over") | P2: =IF(M2<-0.05,"Watch","On Track")
A3: CC-00002 | B3: EVT-2025-001 | C3: Cordavex Internal Meeting Vienna Apr 2025 | D3: Cardiology | E3: BU Cardiovascular | F3: Hotel | G3: Apr-2025 | H3: Q2 2025 | I3: 63210.04 | J3: 38745.02 | K3: 29284.04 | L3: =I3-J3 | M3: =IF(I3=0,0,ROUND((I3-J3)/I3,4)) | N3: =IF(I3=0,0,J3/I3) | O3: =IF(L3>=0,"Under","Over") | P3: =IF(M3<-0.05,"Watch","On Track")
A4: CC-00003 | B4: EVT-2025-001 | C4: Cordavex Internal Meeting Vienna Apr 2025 | D4: Cardiology | E4: BU Cardiovascular | F4: Venue | G4: Apr-2025 | H4: Q2 2025 | I4: 52675.03 | J4: 45241.14 | K4: 44067.71 | L4: =I4-J4 | M4: =IF(I4=0,0,ROUND((I4-J4)/I4,4)) | N4: =IF(I4=0,0,J4/I4) | O4: =IF(L4>=0,"Under","Over") | P4: =IF(M4<-0.05,"Watch","On Track")
A5: CC-00004 | B5: EVT-2025-001 | C5: Cordavex Internal Meeting Vienna Apr 2025 | D5: Cardiology | E5: BU Cardiovascular | F5: F&B | G5: Apr-2025 | H5: Q2 2025 | I5: 42140.03 | J5: 27765.24 | K5: 25890.79 | L5: =I5-J5 | M5: =IF(I5=0,0,ROUND((I5-J5)/I5,4)) | N5: =IF(I5=0,0,J5/I5) | O5: =IF(L5>=0,"Under","Over") | P5: =IF(M5<-0.05,"Watch","On Track")
A6: CC-00005 | B6: EVT-2025-001 | C6: Cordavex Internal Meeting Vienna Apr 2025 | D6: Cardiology | E6: BU Cardiovascular | F6: Logistics | G6: Apr-2025 | H6: Q2 2025 | I6: 21070.01 | J6: 20059.05 | K6: 15332.56 | L6: =I6-J6 | M6: =IF(I6=0,0,ROUND((I6-J6)/I6,4)) | N6: =IF(I6=0,0,J6/I6) | O6: =IF(L6>=0,"Under","Over") | P6: =IF(M6<-0.05,"Watch","On Track")
A7: CC-00006 | B7: EVT-2025-001 | C7: Cordavex Internal Meeting Vienna Apr 2025 | D7: Cardiology | E7: BU Cardiovascular | F7: AV & Technology | G7: Apr-2025 | H7: Q2 2025 | I7: 28093.35 | J7: 25450.85 | K7: 23114.31 | L7: =I7-J7 | M7: =IF(I7=0,0,ROUND((I7-J7)/I7,4)) | N7: =IF(I7=0,0,J7/I7) | O7: =IF(L7>=0,"Under","Over") | P7: =IF(M7<-0.05,"Watch","On Track")
A8: CC-00007 | B8: EVT-2025-001 | C8: Cordavex Internal Meeting Vienna Apr 2025 | D8: Cardiology | E8: BU Cardiovascular | F8: Agency Fees | G8: Apr-2025 | H8: Q2 2025 | I8: 49163.36 | J8: 54045.99 | K8: 41077.84 | L8: =I8-J8 | M8: =IF(I8=0,0,ROUND((I8-J8)/I8,4)) | N8: =IF(I8=0,0,J8/I8) | O8: =IF(L8>=0,"Under","Over") | P8: =IF(M8<-0.05,"Watch","On Track")
A9: CC-00008 | B9: EVT-2025-001 | C9: Cordavex Internal Meeting Vienna Apr 2025 | D9: Cardiology | E9: BU Cardiovascular | F9: Speaker Fees | G9: Apr-2025 | H9: Q2 2025 | I9: 35116.69 | J9: 23453.18 | K9: 16938.25 | L9: =I9-J9 | M9: =IF(I9=0,0,ROUND((I9-J9)/I9,4)) | N9: =IF(I9=0,0,J9/I9) | O9: =IF(L9>=0,"Under","Over") | P9: =IF(M9<-0.05,"Watch","On Track")
A10: CC-00009 | B10: EVT-2025-001 | C10: Cordavex Internal Meeting Vienna Apr 2025 | D10: Cardiology | E10: BU Cardiovascular | F10: Translation | G10: Apr-2025 | H10: Q2 2025 | I10: 10535.01 | J10: 7230.47 | K10: 6608.73 | L10: =I10-J10 | M10: =IF(I10=0,0,ROUND((I10-J10)/I10,4)) | N10: =IF(I10=0,0,J10/I10) | O10: =IF(L10>=0,"Under","Over") | P10: =IF(M10<-0.05,"Watch","On Track")
A11: CC-00010 | B11: EVT-2025-001 | C11: Cordavex Internal Meeting Vienna Apr 2025 | D11: Cardiology | E11: BU Cardiovascular | F11: Print & Production | G11: Apr-2025 | H11: Q2 2025 | I11: 7023.34 | J11: 7716.06 | K11: 7277.43 | L11: =I11-J11 | M11: =IF(I11=0,0,ROUND((I11-J11)/I11,4)) | N11: =IF(I11=0,0,J11/I11) | O11: =IF(L11>=0,"Under","Over") | P11: =IF(M11<-0.05,"Watch","On Track")
A12: CC-00011 | B12: EVT-2025-001 | C12: Cordavex Internal Meeting Vienna Apr 2025 | D12: Cardiology | E12: BU Cardiovascular | F12: Miscellaneous | G12: Apr-2025 | H12: Q2 2025 | I12: 7023.34 | J12: 7611.76 | K12: 7581.1 | L12: =I12-J12 | M12: =IF(I12=0,0,ROUND((I12-J12)/I12,4)) | N12: =IF(I12=0,0,J12/I12) | O12: =IF(L12>=0,"Under","Over") | P12: =IF(M12<-0.05,"Watch","On Track")
A13: CC-00012 | B13: EVT-2025-002 | C13: Eplitazan Investigator Meeting Barcelona Jan 2025 | D13: Cardiology | E13: BU Cardiovascular | F13: Airfare | G13: Jan-2025 | H13: Q1 2025 | I13: 32732.37 | J13: 30569.41 | K13: 0 | L13: =I13-J13 | M13: =IF(I13=0,0,ROUND((I13-J13)/I13,4)) | N13: =IF(I13=0,0,J13/I13) | O13: =IF(L13>=0,"Under","Over") | P13: =IF(M13<-0.05,"Watch","On Track")
... A551: CC-00550 | B551: EVT-2025-050 | C551: Infectoban Launch Event Paris Jun 2025 | D551: Infectious Diseases | E551: BU Infectious Diseases | F551: Miscellaneous | G551: Jun-2025 | H551: Q2 2025 | I551: 4143.79 | J551: 3839.37 | K551: 3158.8 | L551: =I551-J551 | M551: =IF(I551=0,0,ROUND((I551-J551)/I551,4)) | N551: =IF(I551=0,0,J551/I551) | O551: =IF(L551>=0,"Under","Over") | P551: =IF(M551<-0.05,"Watch","On Track")
A553: TOTALS | I553: =SUM(I2:I551) | J553: =SUM(J2:J551) | K553: =SUM(K2:K551) | L553: =SUM(L2:L551)

Sheet PO Tracking
A1: PO Number | B1: Event ID | C1: Supplier | D1: Category | E1: Request Date | F1: Approval Date | G1: Days to Approve | H1: Amount (€) | I1: Currency | J1: Cost Center | K1: GL Account | L1: PO Status | M1: Invoice Number | N1: Payment Status | O1: Due Date | P1: Days Overdue | Q1: Requestor | R1: Approver | S1: Notes
A2: PO-2025-1001 | B2: EVT-2025-001 | C2: Translingua Pro | D2: Translation & Interpretation | E2: 45690 | F2: 45699 | G2: =F2-E2 | H2: 56833.03 | I2: EUR | J2: CC-8272 | K2: GL-6315 | L2: Pending Approval | M2: INV-01001 | N2: Approved | O2: 45751 | P2: 0 | Q2: Marco Bianchi | R2: David O'Brien
A3: PO-2025-1002 | B3: EVT-2025-001 | C3: Catering Excellence | D3: F&B / Catering | E3: 45713 | F3: 45719 | G3: =F3-E3 | H3: 50754.52 | I3: EUR | J3: CC-5785 | K3: GL-6310 | L3: Approved | M3: INV-01002 | N3: Approved | O3: 45744 | P3: 0 | Q3: James Wilson | R3: Lena Schneider
A4: PO-2025-1003 | B4: EVT-2025-001 | C4: AVIAWORLD Travel | D4: Travel & Air | E4: 45713 | F4: 45718 | G4: =F4-E4 | H4: 19535.14 | I4: EUR | J4: CC-8492 | K4: GL-6320 | L4: Cancelled | N4: Cancelled | O4: 45761 | P4: 0 | Q4: Carlos Navarro | R4: Lena Schneider
A5: PO-2025-1004 | B5: EVT-2025-001 | C5: Prime Hospitality Group | D5: Hotel & Venue | E5: 45694 | F5: 45698 | G5: =F5-E5 | H5: 14941.98 | I5: EUR | J5: CC-2871 | K5: GL-6312 | L5: Closed | N5: Cancelled | O5: 45756 | P5: 0 | Q5: Lucas Dupont | R5: Lena Schneider
A6: PO-2025-1005 | B6: EVT-2025-001 | C6: TechEvent Systems | D6: Registration & Tech | E6: 45669 | F6: 45672 | G6: =F6-E6 | H6: 36253.97 | I6: EUR | J6: CC-8231 | K6: GL-6320 | L6: Pending Approval | M6: INV-01005 | N6: Disputed | O6: 45751 | P6: 0 | Q6: Emma Johansson | R6: Marco Bianchi
A7: PO-2025-1006 | B7: EVT-2025-002 | C7: PrintMed Solutions | D7: Print & Production | E7: 45576 | F7: 45582 | G7: =F7-E7 | H7: 48646.86 | I7: EUR | J7: CC-5877 | K7: GL-6330 | L7: Draft | M7: INV-01006 | N7: Overdue | O7: 45653 | P7: 544 | Q7: Carlos Navarro | R7: Isabel Ferreira
A8: PO-2025-1007 | B8: EVT-2025-002 | C8: HealthMarketing Group | D8: Marketing Agency | E8: 45593 | F8: 45597 | G8: =F8-E8 | H8: 19856.1 | I8: EUR | J8: CC-8193 | K8: GL-6330 | L8: Draft | N8: Overdue | O8: 45645 | P8: 552 | Q8: James Wilson | R8: James Wilson
A9: PO-2025-1008 | B9: EVT-2025-002 | C9: Translingua Pro | D9: Translation & Interpretation | E9: 45564 | F9: 45572 | G9: =F9-E9 | H9: 79966.65 | I9: EUR | J9: CC-8015 | K9: GL-6311 | L9: Closed | M9: INV-01008 | N9: Overdue | O9: 45645 | P9: 552 | Q9: Sophie Müller | R9: James Wilson
A10: PO-2025-1009 | B10: EVT-2025-003 | C10: Translingua Pro | D10: Translation & Interpretation | E10: 45676 | F10: 45682 | G10: =F10-E10 | H10: 73453.68 | I10: EUR | J10: CC-1972 | K10: GL-6320 | L10: Approved | M10: INV-01009 | N10: Paid | O10: 45758 | P10: 0 | Q10: Lena Schneider | R10: Isabel Ferreira
A11: PO-2025-1010 | B11: EVT-2025-003 | C11: PrintMed Solutions | D11: Print & Production | E11: 45680 | F11: 45685 | G11: =F11-E11 | H11: 77586.31 | I11: EUR | J11: CC-6302 | K11: GL-6325 | L11: Approved | M11: INV-01010 | N11: Invoiced | O11: 45748 | P11: 0 | Q11: Isabel Ferreira | R11: David O'Brien
A12: PO-2025-1011 | B12: EVT-2025-004 | C12: TechEvent Systems | D12: Registration & Tech | E12: 45731 | F12: 45735 | G12: =F12-E12 | H12: 34108.32 | I12: EUR | J12: CC-3221 | K12: GL-6330 | L12: Sent to Supplier | N12: Paid | O12: 45778 | P12: 0 | Q12: Ana García | R12: Isabel Ferreira
A13: PO-2025-1012 | B13: EVT-2025-005 | C13: AVIAWORLD Travel | D13: Travel & Air | E13: 45863 | F13: 45868 | G13: =F13-E13 | H13: 77674.41 | I13: EUR | J13: CC-3174 | K13: GL-6311 | L13: Pending Approval | M13: INV-01012 | N13: Cancelled | O13: 45948 | P13: 0 | Q13: Thomas Dubois | R13: Lucas Dupont
A14: PO-2025-1013 | B14: EVT-2025-005 | C14: Translingua Pro | D14: Translation & Interpretation | E14: 45864 | F14: 45870 | G14: =F14-E14 | H14: 44322.3 | I14: EUR | J14: CC-7434 | K14: GL-6315 | L14: Pending Approval | M14: INV-01013 | N14: Overdue | O14: 45947 | P14: 250 | Q14: David O'Brien | R14: Maria Kowalski
A15: PO-2025-1014 | B15: EVT-2025-005 | C15: InterCongress PCO | D15: PCO / Event Agency | E15: 45899 | F15: 45908 | G15: =F15-E15 | H15: 40882.46 | I15: EUR | J15: CC-7146 | K15: GL-6315 | L15: Draft | M15: INV-01014 | N15: Approved | O15: 45946 | P15: 0 | Q15: Maria Kowalski | R15: Marco Bianchi
A16: PO-2025-1015 | B16: EVT-2025-005 | C16: PharmaLogix | D16: Logistics & Transport | E16: 45891 | F16: 45898 | G16: =F16-E16 | H16: 74358.48 | I16: EUR | J16: CC-7046 | K16: GL-6315 | L16: Sent to Supplier | M16: INV-01015 | N16: Paid | O16: 45946 | P16: 0 | Q16: Lucas Dupont | R16: David O'Brien
A17: PO-2025-1016 | B17: EVT-2025-005 | C17: Catering Excellence | D17: F&B / Catering | E17: 45923 | F17: 45927 | G17: =F17-E17 | H17: 51141.74 | I17: EUR | J17: CC-8511 | K17: GL-6325 | L17: Cancelled | N17: Invoiced | O17: 45953 | P17: 0 | Q17: Thomas Dubois | R17: Lucas Dupont
A18: PO-2025-1017 | B18: EVT-2025-006 | C18: PrintMed Solutions | D18: Print & Production | E18: 45714 | F18: 45718 | G18: =F18-E18 | H18: 19526.65 | I18: EUR | J18: CC-9756 | K18: GL-6315 | L18: Pending Approval | M18: INV-01017 | N18: Pending | O18: 45798 | P18: 0 | Q18: Emma Johansson | R18: James Wilson
A19: PO-2025-1018 | B19: EVT-2025-007 | C19: Translingua Pro | D19: Translation & Interpretation | E19: 45628 | F19: 45635 | G19: =F19-E19 | H19: 57022.11 | I19: EUR | J19: CC-6289 | K19: GL-6330 | L19: Approved | N19: Paid | O19: 45689 | P19: 0 | Q19: Lucas Dupont | R19: Lena Schneider
A20: PO-2025-1019 | B20: EVT-2025-007 | C20: KOL Connect | D20: Speaker Management | E20: 45630 | F20: 45635 | G20: =F20-E20 | H20: 13282.07 | I20: EUR | J20: CC-8951 | K20: GL-6330 | L20: Approved | M20: INV-01019 | N20: Overdue | O20: 45696 | P20: 501 | Q20: Maria Kowalski | R20: Ana García
A21: PO-2025-1020 | B21: EVT-2025-008 | C21: TechEvent Systems | D21: Registration & Tech | E21: 45949 | F21: 45953 | G21: =F21-E21 | H21: 63620.48 | I21: EUR | J21: CC-8529 | K21: GL-6310 | L21: Draft | N21: Cancelled | O21: 45981 | P21: 0 | Q21: Sophie Müller | R21: Carlos Navarro
A22: PO-2025-1021 | B22: EVT-2025-008 | C22: InterCongress PCO | D22: PCO / Event Agency | E22: 45912 | F22: 45915 | G22: =F22-E22 | H22: 2200.09 | I22: EUR | J22: CC-8009 | K22: GL-6311 | L22: Cancelled | N22: Overdue | O22: 45971 | P22: 226 | Q22: Sophie Müller | R22: Maria Kowalski
A23: PO-2025-1022 | B23: EVT-2025-009 | C23: TechEvent Systems | D23: Registration & Tech | E23: 45821 | F23: 45826 | G23: =F23-E23 | H23: 27930.32 | I23: EUR | J23: CC-5489 | K23: GL-6310 | L23: Cancelled | M23: INV-01022 | N23: Invoiced | O23: 45870 | P23: 0 | Q23: Lucas Dupont | R23: Isabel Ferreira
A24: PO-2025-1023 | B24: EVT-2025-009 | C24: MedAudio AV Solutions | D24: AV & Technology | E24: 45834 | F24: 45842 | G24: =F24-E24 | H24: 56404.88 | I24: EUR | J24: CC-3711 | K24: GL-6310 | L24: Sent to Supplier | N24: Cancelled | O24: 45869 | P24: 0 | Q24: Maria Kowalski | R24: Isabel Ferreira
A25: PO-2025-1024 | B25: EVT-2025-009 | C25: Translingua Pro | D25: Translation & Interpretation | E25: 45796 | F25: 45802 | G25: =F25-E25 | H25: 26817.75 | I25: EUR | J25: CC-8032 | K25: GL-6325 | L25: Draft | M25: INV-01024 | N25: Cancelled | O25: 45872 | P25: 0 | Q25: Thomas Dubois | R25: Marco Bianchi
A26: PO-2025-1025 | B26: EVT-2025-009 | C26: PrintMed Solutions | D26: Print & Production | E26: 45837 | F26: 45843 | G26: =F26-E26 | H26: 53767.73 | I26: EUR | J26: CC-8812 | K26: GL-6310 | L26: Pending Approval | M26: INV-01025 | N26: Paid | O26: 45867 | P26: 0 | Q26: David O'Brien | R26: James Wilson
A27: PO-2025-1026 | B27: EVT-2025-010 | C27: PrintMed Solutions | D27: Print & Production | E27: 45691 | F27: 45701 | G27: =F27-E27 | H27: 9828.44 | I27: EUR | J27: CC-1152 | K27: GL-6310 | L27: Cancelled | M27: INV-01026 | N27: Paid | O27: 45754 | P27: 0 | Q27: Lucas Dupont | R27: Marco Bianchi
A28: PO-2025-1027 | B28: EVT-2025-010 | C28: DigitalPharma Studio | D28: Digital & Web | E28: 45663 | F28: 45672 | G28: =F28-E28 | H28: 33978.33 | I28: EUR | J28: CC-3165 | K28: GL-6315 | L28: Draft | M28: INV-01027 | N28: Pending | O28: 45748 | P28: 0 | Q28: James Wilson | R28: Emma Johansson
A29: PO-2025-1028 | B29: EVT-2025-011 | C29: PharmaLogix | D29: Logistics & Transport | E29: 45941 | F29: 45945 | G29: =F29-E29 | H29: 8264.6 | I29: EUR | J29: CC-2690 | K29: GL-6312 | L29: Approved | M29: INV-01028 | N29: Cancelled | O29: 45976 | P29: 0 | Q29: Isabel Ferreira | R29: Sophie Müller
A30: PO-2025-1029 | B30: EVT-2025-011 | C30: DigitalPharma Studio | D30: Digital & Web | E30: 45910 | F30: 45915 | G30: =F30-E30 | H30: 26699.57 | I30: EUR | J30: CC-3340 | K30: GL-6310 | L30: Closed | M30: INV-01029 | N30: Paid | O30: 45964 | P30: 0 | Q30: David O'Brien | R30: Ana García
A31: PO-2025-1030 | B31: EVT-2025-011 | C31: KOL Connect | D31: Speaker Management | E31: 45910 | F31: 45915 | G31: =F31-E31 | H31: 50161.84 | I31: EUR | J31: CC-8210 | K31: GL-6312 | L31: Cancelled | M31: INV-01030 | N31: Invoiced | O31: 45979 | P31: 0 | Q31: James Wilson | R31: Maria Kowalski
A32: PO-2025-1031 | B32: EVT-2025-012 | C32: MedComm Agency | D32: Medical Communication | E32: 45827 | F32: 45832 | G32: =F32-E32 | H32: 61308.84 | I32: EUR | J32: CC-7745 | K32: GL-6320 | L32: Cancelled | M32: INV-01031 | N32: Paid | O32: 45904 | P32: 0 | Q32: Carlos Navarro | R32: James Wilson
A33: PO-2025-1032 | B33: EVT-2025-013 | C33: HealthMarketing Group | D33: Marketing Agency | E33: 45865 | F33: 45869 | G33: =F33-E33 | H33: 6377.3 | I33: EUR | J33: CC-3293 | K33: GL-6330 | L33: Draft | M33: INV-01032 | N33: Approved | O33: 45900 | P33: 0 | Q33: David O'Brien | R33: Thomas Dubois
A34: PO-2025-1033 | B34: EVT-2025-013 | C34: AVIAWORLD Travel | D34: Travel & Air | E34: 45852 | F34: 45860 | G34: =F34-E34 | H34: 46142.39 | I34: EUR | J34: CC-8035 | K34: GL-6312 | L34: Pending Approval | M34: INV-01033 | N34: Pending | O34: 45906 | P34: 0 | Q34: James Wilson | R34: Isabel Ferreira
A35: PO-2025-1034 | B35: EVT-2025-013 | C35: TechEvent Systems | D35: Registration & Tech | E35: 45833 | F35: 45837 | G35: =F35-E35 | H35: 50337.41 | I35: EUR | J35: CC-5065 | K35: GL-6320 | L35: Closed | M35: INV-01034 | N35: Overdue | O35: 45904 | P35: 293 | Q35: David O'Brien | R35: Thomas Dubois
A36: PO-2025-1035 | B36: EVT-2025-014 | C36: Translingua Pro | D36: Translation & Interpretation | E36: 45888 | F36: 45895 | G36: =F36-E36 | H36: 21915.48 | I36: EUR | J36: CC-1439 | K36: GL-6330 | L36: Cancelled | N36: Paid | O36: 45956 | P36: 0 | Q36: Isabel Ferreira | R36: James Wilson
A37: PO-2025-1036 | B37: EVT-2025-014 | C37: Compliance Expert Ltd | D37: Compliance & Legal | E37: 45879 | F37: 45885 | G37: =F37-E37 | H37: 14322.1 | I37: EUR | J37: CC-7418 | K37: GL-6312 | L37: Cancelled | M37: INV-01036 | N37: Overdue | O37: 45942 | P37: 255 | Q37: Ana García | R37: James Wilson
A38: PO-2025-1037 | B38: EVT-2025-015 | C38: KOL Connect | D38: Speaker Management | E38: 45924 | F38: 45933 | G38: =F38-E38 | H38: 32006.07 | I38: EUR | J38: CC-2847 | K38: GL-6311 | L38: Sent to Supplier | N38: Paid | O38: 45985 | P38: 0 | Q38: Maria Kowalski | R38: David O'Brien
A39: PO-2025-1038 | B39: EVT-2025-015 | C39: Catering Excellence | D39: F&B / Catering | E39: 45944 | F39: 45947 | G39: =F39-E39 | H39: 25078.05 | I39: EUR | J39: CC-6916 | K39: GL-6312 | L39: Pending Approval | M39: INV-01038 | N39: Cancelled | O39: 45978 | P39: 0 | Q39: Emma Johansson | R39: David O'Brien
A40: PO-2025-1039 | B40: EVT-2025-015 | C40: Translingua Pro | D40: Translation & Interpretation | E40: 45923 | F40: 45931 | G40: =F40-E40 | H40: 2631.64 | I40: EUR | J40: CC-9951 | K40: GL-6325 | L40: Pending Approval | M40: INV-01039 | N40: Pending | O40: 45979 | P40: 0 | Q40: Carlos Navarro | R40: Marco Bianchi
A41: PO-2025-1040 | B41: EVT-2025-015 | C41: TechEvent Systems | D41: Registration & Tech | E41: 45960 | F41: 45964 | G41: =F41-E41 | H41: 66961.43 | I41: EUR | J41: CC-1225 | K41: GL-6312 | L41: Pending Approval | M41: INV-01040 | N41: Approved | O41: 45991 | P41: 0 | Q41: Ana García | R41: Ana García
A42: PO-2025-1041 | B42: EVT-2025-016 | C42: Prime Hospitality Group | D42: Hotel & Venue | E42: 45539 | F42: 45548 | G42: =F42-E42 | H42: 54865.63 | I42: EUR | J42: CC-9300 | K42: GL-6312 | L42: Cancelled | M42: INV-01041 | N42: Disputed | O42: 45629 | P42: 0 | Q42: Thomas Dubois | R42: Lena Schneider
A43: PO-2025-1042 | B43: EVT-2025-016 | C43: Compliance Expert Ltd | D43: Compliance & Legal | E43: 45553 | F43: 45562 | G43: =F43-E43 | H43: 9578.79 | I43: EUR | J43: CC-7939 | K43: GL-6325 | L43: Sent to Supplier | N43: Invoiced | O43: 45632 | P43: 0 | Q43: Marco Bianchi | R43: Maria Kowalski
A44: PO-2025-1043 | B44: EVT-2025-016 | C44: HealthMarketing Group | D44: Marketing Agency | E44: 45565 | F44: 45570 | G44: =F44-E44 | H44: 47206.76 | I44: EUR | J44: CC-5546 | K44: GL-6310 | L44: Approved | M44: INV-01043 | N44: Invoiced | O44: 45629 | P44: 0 | Q44: Marco Bianchi | R44: Lena Schneider
A45: PO-2025-1044 | B45: EVT-2025-017 | C45: MedAudio AV Solutions | D45: AV & Technology | E45: 45858 | F45: 45864 | G45: =F45-E45 | H45: 30536.89 | I45: EUR | J45: CC-3545 | K45: GL-6320 | L45: Approved | M45: INV-01044 | N45: Cancelled | O45: 45946 | P45: 0 | Q45: Emma Johansson | R45: David O'Brien
A46: PO-2025-1045 | B46: EVT-2025-017 | C46: Prime Hospitality Group | D46: Hotel & Venue | E46: 45877 | F46: 45881 | G46: =F46-E46 | H46: 66325.81 | I46: EUR | J46: CC-6081 | K46: GL-6325 | L46: Sent to Supplier | N46: Invoiced | O46: 45947 | P46: 0 | Q46: Thomas Dubois | R46: James Wilson
A47: PO-2025-1046 | B47: EVT-2025-017 | C47: HealthMarketing Group | D47: Marketing Agency | E47: 45915 | F47: 45921 | G47: =F47-E47 | H47: 64730.14 | I47: EUR | J47: CC-2412 | K47: GL-6315 | L47: Draft | M47: INV-01046 | N47: Approved | O47: 45948 | P47: 0 | Q47: Carlos Navarro | R47: David O'Brien
A48: PO-2025-1047 | B48: EVT-2025-017 | C48: PrintMed Solutions | D48: Print & Production | E48: 45871 | F48: 45874 | G48: =F48-E48 | H48: 69090.97 | I48: EUR | J48: CC-6067 | K48: GL-6325 | L48: Cancelled | M48: INV-01047 | N48: Paid | O48: 45939 | P48: 0 | Q48: Maria Kowalski | R48: Thomas Dubois
A49: PO-2025-1048 | B49: EVT-2025-018 | C49: PharmaLogix | D49: Logistics & Transport | E49: 45608 | F49: 45612 | G49: =F49-E49 | H49: 11639.92 | I49: EUR | J49: CC-1207 | K49: GL-6325 | L49: Pending Approval | N49: Disputed | O49: 45649 | P49: 0 | Q49: Thomas Dubois | R49: Ana García
A50: PO-2025-1049 | B50: EVT-2025-018 | C50: InterCongress PCO | D50: PCO / Event Agency | E50: 45609 | F50: 45619 | G50: =F50-E50 | H50: 66148.55 | I50: EUR | J50: CC-6680 | K50: GL-6320 | L50: Closed | M50: INV-01049 | N50: Approved | O50: 45649 | P50: 0 | Q50: Thomas Dubois | R50: Isabel Ferreira
A51: PO-2025-1050 | B51: EVT-2025-018 | C51: Venue Masters EMEA | D51: Venue Sourcing | E51: 45603 | F51: 45611 | G51: =F51-E51 | H51: 70970.32 | I51: EUR | J51: CC-3079 | K51: GL-6325 | L51: Approved | N51: Overdue | O51: 45643 | P51: 554 | Q51: Thomas Dubois | R51: Marco Bianchi
A52: PO-2025-1051 | B52: EVT-2025-018 | C52: MedComm Agency | D52: Medical Communication | E52: 45567 | F52: 45570 | G52: =F52-E52 | H52: 51561.51 | I52: EUR | J52: CC-6488 | K52: GL-6330 | L52: Sent to Supplier | M52: INV-01051 | N52: Invoiced | O52: 45646 | P52: 0 | Q52: Isabel Ferreira | R52: Lena Schneider
A53: PO-2025-1052 | B53: EVT-2025-018 | C53: AVIAWORLD Travel | D53: Travel & Air | E53: 45625 | F53: 45632 | G53: =F53-E53 | H53: 12902.61 | I53: EUR | J53: CC-2262 | K53: GL-6315 | L53: Sent to Supplier | M53: INV-01052 | N53: Paid | O53: 45659 | P53: 0 | Q53: Lena Schneider | R53: Lucas Dupont
A54: PO-2025-1053 | B54: EVT-2025-019 | C54: Prime Hospitality Group | D54: Hotel & Venue | E54: 45852 | F54: 45862 | G54: =F54-E54 | H54: 12581.8 | I54: EUR | J54: CC-3734 | K54: GL-6312 | L54: Pending Approval | M54: INV-01053 | N54: Disputed | O54: 45885 | P54: 0 | Q54: Isabel Ferreira | R54: Marco Bianchi
A55: PO-2025-1054 | B55: EVT-2025-020 | C55: MedComm Agency | D55: Medical Communication | E55: 45633 | F55: 45637 | G55: =F55-E55 | H55: 53083.91 | I55: EUR | J55: CC-4742 | K55: GL-6325 | L55: Closed | M55: INV-01054 | N55: Invoiced | O55: 45720 | P55: 0 | Q55: Ana García | R55: Ana García
A56: PO-2025-1055 | B56: EVT-2025-020 | C56: DigitalPharma Studio | D56: Digital & Web | E56: 45637 | F56: 45640 | G56: =F56-E56 | H56: 18947.04 | I56: EUR | J56: CC-5006 | K56: GL-6310 | L56: Sent to Supplier | M56: INV-01055 | N56: Cancelled | O56: 45721 | P56: 0 | Q56: Lucas Dupont | R56: Emma Johansson
A57: PO-2025-1056 | B57: EVT-2025-020 | C57: KOL Connect | D57: Speaker Management | E57: 45630 | F57: 45635 | G57: =F57-E57 | H57: 55483.06 | I57: EUR | J57: CC-3932 | K57: GL-6330 | L57: Draft | N57: Disputed | O57: 45718 | P57: 0 | Q57: Lena Schneider | R57: Thomas Dubois
A58: PO-2025-1057 | B58: EVT-2025-020 | C58: Venue Masters EMEA | D58: Venue Sourcing | E58: 45655 | F58: 45664 | G58: =F58-E58 | H58: 23518.75 | I58: EUR | J58: CC-4678 | K58: GL-6312 | L58: Pending Approval | N58: Cancelled | O58: 45732 | P58: 0 | Q58: Emma Johansson | R58: Thomas Dubois
A59: PO-2025-1058 | B59: EVT-2025-020 | C59: MedAudio AV Solutions | D59: AV & Technology | E59: 45665 | F59: 45672 | G59: =F59-E59 | H59: 18544.25 | I59: EUR | J59: CC-2276 | K59: GL-6320 | L59: Approved | N59: Pending | O59: 45715 | P59: 0 | Q59: Marco Bianchi | R59: Lena Schneider
A60: PO-2025-1059 | B60: EVT-2025-021 | C60: Prime Hospitality Group | D60: Hotel & Venue | E60: 45765 | F60: 45768 | G60: =F60-E60 | H60: 7351.59 | I60: EUR | J60: CC-3938 | K60: GL-6311 | L60: Closed | M60: INV-01059 | N60: Approved | O60: 45838 | P60: 0 | Q60: Ana García | R60: Emma Johansson
A61: PO-2025-1060 | B61: EVT-2025-021 | C61: MedAudio AV Solutions | D61: AV & Technology | E61: 45817 | F61: 45827 | G61: =F61-E61 | H61: 27627.65 | I61: EUR | J61: CC-5625 | K61: GL-6330 | L61: Approved | M61: INV-01060 | N61: Overdue | O61: 45851 | P61: 346 | Q61: Lucas Dupont | R61: Marco Bianchi
A62: PO-2025-1061 | B62: EVT-2025-021 | C62: Venue Masters EMEA | D62: Venue Sourcing | E62: 45786 | F62: 45796 | G62: =F62-E62 | H62: 78754.19 | I62: EUR | J62: CC-1130 | K62: GL-6312 | L62: Pending Approval | N62: Cancelled | O62: 45851 | P62: 0 | Q62: Isabel Ferreira | R62: David O'Brien
A63: PO-2025-1062 | B63: EVT-2025-022 | C63: Compliance Expert Ltd | D63: Compliance & Legal | E63: 45570 | F63: 45577 | G63: =F63-E63 | H63: 12280.65 | I63: EUR | J63: CC-4974 | K63: GL-6315 | L63: Approved | M63: INV-01062 | N63: Approved | O63: 45650 | P63: 0 | Q63: David O'Brien | R63: Carlos Navarro
A64: PO-2025-1063 | B64: EVT-2025-023 | C64: AVIAWORLD Travel | D64: Travel & Air | E64: 45725 | F64: 45731 | G64: =F64-E64 | H64: 59854.01 | I64: EUR | J64: CC-9954 | K64: GL-6330 | L64: Pending Approval | N64: Pending | O64: 45804 | P64: 0 | Q64: Sophie Müller | R64: Ana García
A65: PO-2025-1064 | B65: EVT-2025-023 | C65: MedAudio AV Solutions | D65: AV & Technology | E65: 45713 | F65: 45722 | G65: =F65-E65 | H65: 30239.04 | I65: EUR | J65: CC-1391 | K65: GL-6311 | L65: Closed | M65: INV-01064 | N65: Overdue | O65: 45802 | P65: 395 | Q65: Lucas Dupont | R65: Maria Kowalski
A66: PO-2025-1065 | B66: EVT-2025-023 | C66: Catering Excellence | D66: F&B / Catering | E66: 45716 | F66: 45719 | G66: =F66-E66 | H66: 5382.47 | I66: EUR | J66: CC-6488 | K66: GL-6310 | L66: Cancelled | M66: INV-01065 | N66: Paid | O66: 45799 | P66: 0 | Q66: Emma Johansson | R66: Thomas Dubois
A67: PO-2025-1066 | B67: EVT-2025-024 | C67: AVIAWORLD Travel | D67: Travel & Air | E67: 45857 | F67: 45864 | G67: =F67-E67 | H67: 68089.29 | I67: EUR | J67: CC-2703 | K67: GL-6311 | L67: Closed | M67: INV-01066 | N67: Paid | O67: 45933 | P67: 0 | Q67: James Wilson | R67: Emma Johansson
A68: PO-2025-1067 | B68: EVT-2025-025 | C68: InterCongress PCO | D68: PCO / Event Agency | E68: 45752 | F68: 45755 | G68: =F68-E68 | H68: 11842.94 | I68: EUR | J68: CC-3332 | K68: GL-6325 | L68: Approved | N68: Overdue | O68: 45813 | P68: 384 | Q68: Marco Bianchi | R68: Ana García
A69: PO-2025-1068 | B69: EVT-2025-025 | C69: HealthMarketing Group | D69: Marketing Agency | E69: 45728 | F69: 45734 | G69: =F69-E69 | H69: 79580.96 | I69: EUR | J69: CC-9515 | K69: GL-6315 | L69: Cancelled | M69: INV-01068 | N69: Overdue | O69: 45816 | P69: 381 | Q69: Lucas Dupont | R69: Carlos Navarro
A70: PO-2025-1069 | B70: EVT-2025-025 | C70: PharmaLogix | D70: Logistics & Transport | E70: 45752 | F70: 45756 | G70: =F70-E70 | H70: 63861.5 | I70: EUR | J70: CC-2565 | K70: GL-6320 | L70: Pending Approval | M70: INV-01069 | N70: Disputed | O70: 45829 | P70: 0 | Q70: Maria Kowalski | R70: Emma Johansson
A71: PO-2025-1070 | B71: EVT-2025-025 | C71: DigitalPharma Studio | D71: Digital & Web | E71: 45785 | F71: 45788 | G71: =F71-E71 | H71: 69508.4 | I71: EUR | J71: CC-8126 | K71: GL-6325 | L71: Pending Approval | M71: INV-01070 | N71: Approved | O71: 45819 | P71: 0 | Q71: James Wilson | R71: Isabel Ferreira
A72: PO-2025-1071 | B72: EVT-2025-026 | C72: TechEvent Systems | D72: Registration & Tech | E72: 45647 | F72: 45655 | G72: =F72-E72 | H72: 9416.7 | I72: EUR | J72: CC-7438 | K72: GL-6325 | L72: Cancelled | M72: INV-01071 | N72: Invoiced | O72: 45693 | P72: 0 | Q72: Lucas Dupont | R72: Lucas Dupont
A73: PO-2025-1072 | B73: EVT-2025-026 | C73: Translingua Pro | D73: Translation & Interpretation | E73: 45633 | F73: 45640 | G73: =F73-E73 | H73: 55572.04 | I73: EUR | J73: CC-4827 | K73: GL-6310 | L73: Pending Approval | M73: INV-01072 | N73: Cancelled | O73: 45691 | P73: 0 | Q73: Sophie Müller | R73: David O'Brien
A74: PO-2025-1073 | B74: EVT-2025-026 | C74: MedComm Agency | D74: Medical Communication | E74: 45647 | F74: 45652 | G74: =F74-E74 | H74: 9532.03 | I74: EUR | J74: CC-2731 | K74: GL-6311 | L74: Sent to Supplier | N74: Approved | O74: 45683 | P74: 0 | Q74: Carlos Navarro | R74: Lucas Dupont
A75: PO-2025-1074 | B75: EVT-2025-027 | C75: DigitalPharma Studio | D75: Digital & Web | E75: 45701 | F75: 45705 | G75: =F75-E75 | H75: 45811.3 | I75: EUR | J75: CC-9780 | K75: GL-6312 | L75: Pending Approval | M75: INV-01074 | N75: Invoiced | O75: 45757 | P75: 0 | Q75: Carlos Navarro | R75: Isabel Ferreira
A76: PO-2025-1075 | B76: EVT-2025-028 | C76: TechEvent Systems | D76: Registration & Tech | E76: 45782 | F76: 45789 | G76: =F76-E76 | H76: 29428.4 | I76: EUR | J76: CC-2964 | K76: GL-6310 | L76: Pending Approval | M76: INV-01075 | N76: Approved | O76: 45841 | P76: 0 | Q76: Maria Kowalski | R76: Isabel Ferreira
A77: PO-2025-1076 | B77: EVT-2025-028 | C77: KOL Connect | D77: Speaker Management | E77: 45766 | F77: 45769 | G77: =F77-E77 | H77: 68087.44 | I77: EUR | J77: CC-4522 | K77: GL-6330 | L77: Approved | M77: INV-01076 | N77: Invoiced | O77: 45848 | P77: 0 | Q77: Sophie Müller | R77: Marco Bianchi
A78: PO-2025-1077 | B78: EVT-2025-028 | C78: AVIAWORLD Travel | D78: Travel & Air | E78: 45771 | F78: 45777 | G78: =F78-E78 | H78: 46779.8 | I78: EUR | J78: CC-6828 | K78: GL-6315 | L78: Closed | M78: INV-01077 | N78: Cancelled | O78: 45846 | P78: 0 | Q78: Ana García | R78: Maria Kowalski
A79: PO-2025-1078 | B79: EVT-2025-028 | C79: Catering Excellence | D79: F&B / Catering | E79: 45793 | F79: 45800 | G79: =F79-E79 | H79: 54648.18 | I79: EUR | J79: CC-3848 | K79: GL-6310 | L79: Sent to Supplier | M79: INV-01078 | N79: Disputed | O79: 45842 | P79: 0 | Q79: Carlos Navarro | R79: Lena Schneider
A80: PO-2025-1079 | B80: EVT-2025-029 | C80: AVIAWORLD Travel | D80: Travel & Air | E80: 45699 | F80: 45705 | G80: =F80-E80 | H80: 26100.81 | I80: EUR | J80: CC-2551 | K80: GL-6315 | L80: Draft | M80: INV-01079 | N80: Approved | O80: 45776 | P80: 0 | Q80: Sophie Müller | R80: Marco Bianchi
A81: PO-2025-1080 | B81: EVT-2025-029 | C81: MedAudio AV Solutions | D81: AV & Technology | E81: 45754 | F81: 45757 | G81: =F81-E81 | H81: 53272.88 | I81: EUR | J81: CC-4641 | K81: GL-6311 | L81: Pending Approval | N81: Disputed | O81: 45784 | P81: 0 | Q81: Emma Johansson | R81: Lucas Dupont
A82: PO-2025-1081 | B82: EVT-2025-029 | C82: Catering Excellence | D82: F&B / Catering | E82: 45701 | F82: 45705 | G82: =F82-E82 | H82: 43377.65 | I82: EUR | J82: CC-5240 | K82: GL-6330 | L82: Draft | N82: Invoiced | O82: 45774 | P82: 0 | Q82: Ana García | R82: Marco Bianchi
A83: PO-2025-1082 | B83: EVT-2025-030 | C83: Catering Excellence | D83: F&B / Catering | E83: 45718 | F83: 45728 | G83: =F83-E83 | H83: 46272.3 | I83: EUR | J83: CC-3110 | K83: GL-6310 | L83: Approved | M83: INV-01082 | N83: Approved | O83: 45760 | P83: 0 | Q83: Marco Bianchi | R83: Ana García
A84: PO-2025-1083 | B84: EVT-2025-030 | C84: KOL Connect | D84: Speaker Management | E84: 45670 | F84: 45680 | G84: =F84-E84 | H84: 5881.47 | I84: EUR | J84: CC-1829 | K84: GL-6311 | L84: Closed | M84: INV-01083 | N84: Disputed | O84: 45760 | P84: 0 | Q84: Emma Johansson | R84: Thomas Dubois
A85: PO-2025-1084 | B85: EVT-2025-030 | C85: PharmaLogix | D85: Logistics & Transport | E85: 45699 | F85: 45709 | G85: =F85-E85 | H85: 36479.45 | I85: EUR | J85: CC-1483 | K85: GL-6315 | L85: Cancelled | M85: INV-01084 | N85: Overdue | O85: 45754 | P85: 443 | Q85: Emma Johansson | R85: Sophie Müller
A86: PO-2025-1085 | B86: EVT-2025-031 | C86: MedComm Agency | D86: Medical Communication | E86: 45827 | F86: 45833 | G86: =F86-E86 | H86: 48264.47 | I86: EUR | J86: CC-4066 | K86: GL-6312 | L86: Approved | M86: INV-01085 | N86: Pending | O86: 45879 | P86: 0 | Q86: Carlos Navarro | R86: Sophie Müller
A87: PO-2025-1086 | B87: EVT-2025-031 | C87: InterCongress PCO | D87: PCO / Event Agency | E87: 45863 | F87: 45869 | G87: =F87-E87 | H87: 48747.35 | I87: EUR | J87: CC-5835 | K87: GL-6315 | L87: Sent to Supplier | M87: INV-01086 | N87: Approved | O87: 45895 | P87: 0 | Q87: Lena Schneider | R87: Carlos Navarro
A88: PO-2025-1087 | B88: EVT-2025-031 | C88: Catering Excellence | D88: F&B / Catering | E88: 45852 | F88: 45856 | G88: =F88-E88 | H88: 21930.52 | I88: EUR | J88: CC-5583 | K88: GL-6315 | L88: Pending Approval | N88: Paid | O88: 45885 | P88: 0 | Q88: Emma Johansson | R88: James Wilson
A89: PO-2025-1088 | B89: EVT-2025-032 | C89: MedAudio AV Solutions | D89: AV & Technology | E89: 45593 | F89: 45599 | G89: =F89-E89 | H89: 41020.46 | I89: EUR | J89: CC-9907 | K89: GL-6330 | L89: Draft | M89: INV-01088 | N89: Pending | O89: 45664 | P89: 0 | Q89: Emma Johansson | R89: Thomas Dubois
A90: PO-2025-1089 | B90: EVT-2025-032 | C90: HealthMarketing Group | D90: Marketing Agency | E90: 45633 | F90: 45643 | G90: =F90-E90 | H90: 5299.58 | I90: EUR | J90: CC-9921 | K90: GL-6330 | L90: Sent to Supplier | M90: INV-01089 | N90: Pending | O90: 45685 | P90: 0 | Q90: Lucas Dupont | R90: David O'Brien
A91: PO-2025-1090 | B91: EVT-2025-032 | C91: MedComm Agency | D91: Medical Communication | E91: 45611 | F91: 45619 | G91: =F91-E91 | H91: 35484.17 | I91: EUR | J91: CC-7363 | K91: GL-6312 | L91: Pending Approval | M91: INV-01090 | N91: Paid | O91: 45673 | P91: 0 | Q91: Ana García | R91: Lucas Dupont
A92: PO-2025-1091 | B92: EVT-2025-032 | C92: PrintMed Solutions | D92: Print & Production | E92: 45607 | F92: 45613 | G92: =F92-E92 | H92: 3626.81 | I92: EUR | J92: CC-1480 | K92: GL-6330 | L92: Approved | N92: Overdue | O92: 45675 | P92: 522 | Q92: Ana García | R92: Carlos Navarro
A93: PO-2025-1092 | B93: EVT-2025-033 | C93: InterCongress PCO | D93: PCO / Event Agency | E93: 45908 | F93: 45916 | G93: =F93-E93 | H93: 47931.96 | I93: EUR | J93: CC-4813 | K93: GL-6311 | L93: Draft | N93: Cancelled | O93: 45971 | P93: 0 | Q93: James Wilson | R93: Maria Kowalski
A94: PO-2025-1093 | B94: EVT-2025-033 | C94: MedComm Agency | D94: Medical Communication | E94: 45937 | F94: 45944 | G94: =F94-E94 | H94: 19282.62 | I94: EUR | J94: CC-9743 | K94: GL-6330 | L94: Cancelled | M94: INV-01093 | N94: Disputed | O94: 45982 | P94: 0 | Q94: Ana García | R94: James Wilson
A95: PO-2025-1094 | B95: EVT-2025-033 | C95: HealthMarketing Group | D95: Marketing Agency | E95: 45910 | F95: 45919 | G95: =F95-E95 | H95: 17124.49 | I95: EUR | J95: CC-6813 | K95: GL-6330 | L95: Pending Approval | M95: INV-01094 | N95: Cancelled | O95: 45976 | P95: 0 | Q95: Sophie Müller | R95: James Wilson
A96: PO-2025-1095 | B96: EVT-2025-034 | C96: Prime Hospitality Group | D96: Hotel & Venue | E96: 45632 | F96: 45640 | G96: =F96-E96 | H96: 17387.2 | I96: EUR | J96: CC-6878 | K96: GL-6320 | L96: Draft | N96: Cancelled | O96: 45699 | P96: 0 | Q96: Thomas Dubois | R96: Thomas Dubois
A97: PO-2025-1096 | B97: EVT-2025-034 | C97: InterCongress PCO | D97: PCO / Event Agency | E97: 45646 | F97: 45651 | G97: =F97-E97 | H97: 76200.79 | I97: EUR | J97: CC-4084 | K97: GL-6330 | L97: Sent to Supplier | N97: Cancelled | O97: 45698 | P97: 0 | Q97: Lena Schneider | R97: Isabel Ferreira
A98: PO-2025-1097 | B98: EVT-2025-035 | C98: Translingua Pro | D98: Translation & Interpretation | E98: 45849 | F98: 45859 | G98: =F98-E98 | H98: 27210.24 | I98: EUR | J98: CC-1621 | K98: GL-6310 | L98: Draft | M98: INV-01097 | N98: Paid | O98: 45890 | P98: 0 | Q98: James Wilson | R98: David O'Brien
A99: PO-2025-1098 | B99: EVT-2025-035 | C99: Compliance Expert Ltd | D99: Compliance & Legal | E99: 45858 | F99: 45861 | G99: =F99-E99 | H99: 51248.04 | I99: EUR | J99: CC-9625 | K99: GL-6315 | L99: Draft | M99: INV-01098 | N99: Invoiced | O99: 45902 | P99: 0 | Q99: Lucas Dupont | R99: David O'Brien
A100: PO-2025-1099 | B100: EVT-2025-035 | C100: DigitalPharma Studio | D100: Digital & Web | E100: 45867 | F100: 45872 | G100: =F100-E100 | H100: 38015.91 | I100: EUR | J100: CC-6582 | K100: GL-6325 | L100: Pending Approval | N100: Cancelled | O100: 45909 | P100: 0 | Q100: Lucas Dupont | R100: Ana García
...

Sheet Executive Reporting
A1: PHARMACEUTICAL EVENTS – EXECUTIVE FINANCIAL REPORTING | FY 2025
A2: Report Date: 24 June 2026 | Confidential | Finance & PMO
A4: 1. MONTHLY FINANCIAL SUMMARY
A5: Month | B5: # Events | C5: Budget (€) | D5: Committed (€) | E5: Actual (€) | F5: Forecast (€) | G5: Variance (€) | H5: Var % | I5: Budget Absorption % | J5: Status
A6: Jan | B6: =SUMPRODUCT((MONTH('Budget Planning'!$H$2:$H$51)=1)*(YEAR('Budget Planning'!$H$2:$H$51)=2025)*1) | C6: =SUMPRODUCT((MONTH('Budget Planning'!$H$2:$H$51)=1)*(YEAR('Budget Planning'!$H$2:$H$51)=2025)*'Budget Planning'!$J$2:$J$51) | D6: =SUMPRODUCT((MONTH('Budget Planning'!$H$2:$H$51)=1)*(YEAR('Budget Planning'!$H$2:$H$51)=2025)*'Budget Planning'!$N$2:$N$51) | E6: =SUMPRODUCT((MONTH('Budget Planning'!$H$2:$H$51)=1)*(YEAR('Budget Planning'!$H$2:$H$51)=2025)*'Budget Planning'!$O$2:$O$51) | F6: =SUMPRODUCT((MONTH('Budget Planning'!$H$2:$H$51)=1)*(YEAR('Budget Planning'!$H$2:$H$51)=2025)*'Budget Planning'!$M$2:$M$51) | G6: =C6-F6 | H6: =IF(C6=0,0,G6/C6) | I6: =IF(C6=0,0,D6/C6) | J6: =IF(H6<-0.05,"At Risk","On Track")
A7: Feb | B7: =SUMPRODUCT((MONTH('Budget Planning'!$H$2:$H$51)=2)*(YEAR('Budget Planning'!$H$2:$H$51)=2025)*1) | C7: =SUMPRODUCT((MONTH('Budget Planning'!$H$2:$H$51)=2)*(YEAR('Budget Planning'!$H$2:$H$51)=2025)*'Budget Planning'!$J$2:$J$51) | D7: =SUMPRODUCT((MONTH('Budget Planning'!$H$2:$H$51)=2)*(YEAR('Budget Planning'!$H$2:$H$51)=2025)*'Budget Planning'!$N$2:$N$51) | E7: =SUMPRODUCT((MONTH('Budget Planning'!$H$2:$H$51)=2)*(YEAR('Budget Planning'!$H$2:$H$51)=2025)*'Budget Planning'!$O$2:$O$51) | F7: =SUMPRODUCT((MONTH('Budget Planning'!$H$2:$H$51)=2)*(YEAR('Budget Planning'!$H$2:$H$51)=2025)*'Budget Planning'!$M$2:$M$51) | G7: =C7-F7 | H7: =IF(C7=0,0,G7/C7) | I7: =IF(C7=0,0,D7/C7) | J7: =IF(H7<-0.05,"At Risk","On Track")
A8: Mar | B8: =SUMPRODUCT((MONTH('Budget Planning'!$H$2:$H$51)=3)*(YEAR('Budget Planning'!$H$2:$H$51)=2025)*1) | C8: =SUMPRODUCT((MONTH('Budget Planning'!$H$2:$H$51)=3)*(YEAR('Budget Planning'!$H$2:$H$51)=2025)*'Budget Planning'!$J$2:$J$51) | D8: =SUMPRODUCT((MONTH('Budget Planning'!$H$2:$H$51)=3)*(YEAR('Budget Planning'!$H$2:$H$51)=2025)*'Budget Planning'!$N$2:$N$51) | E8: =SUMPRODUCT((MONTH('Budget Planning'!$H$2:$H$51)=3)*(YEAR('Budget Planning'!$H$2:$H$51)=2025)*'Budget Planning'!$O$2:$O$51) | F8: =SUMPRODUCT((MONTH('Budget Planning'!$H$2:$H$51)=3)*(YEAR('Budget Planning'!$H$2:$H$51)=2025)*'Budget Planning'!$M$2:$M$51) | G8: =C8-F8 | H8: =IF(C8=0,0,G8/C8) | I8: =IF(C8=0,0,D8/C8) | J8: =IF(H8<-0.05,"At Risk","On Track")
A9: Apr | B9: =SUMPRODUCT((MONTH('Budget Planning'!$H$2:$H$51)=4)*(YEAR('Budget Planning'!$H$2:$H$51)=2025)*1) | C9: =SUMPRODUCT((MONTH('Budget Planning'!$H$2:$H$51)=4)*(YEAR('Budget Planning'!$H$2:$H$51)=2025)*'Budget Planning'!$J$2:$J$51) | D9: =SUMPRODUCT((MONTH('Budget Planning'!$H$2:$H$51)=4)*(YEAR('Budget Planning'!$H$2:$H$51)=2025)*'Budget Planning'!$N$2:$N$51) | E9: =SUMPRODUCT((MONTH('Budget Planning'!$H$2:$H$51)=4)*(YEAR('Budget Planning'!$H$2:$H$51)=2025)*'Budget Planning'!$O$2:$O$51) | F9: =SUMPRODUCT((MONTH('Budget Planning'!$H$2:$H$51)=4)*(YEAR('Budget Planning'!$H$2:$H$51)=2025)*'Budget Planning'!$M$2:$M$51) | G9: =C9-F9 | H9: =IF(C9=0,0,G9/C9) | I9: =IF(C9=0,0,D9/C9) | J9: =IF(H9<-0.05,"At Risk","On Track")
A10: May | B10: =SUMPRODUCT((MONTH('Budget Planning'!$H$2:$H$51)=5)*(YEAR('Budget Planning'!$H$2:$H$51)=2025)*1) | C10: =SUMPRODUCT((MONTH('Budget Planning'!$H$2:$H$51)=5)*(YEAR('Budget Planning'!$H$2:$H$51)=2025)*'Budget Planning'!$J$2:$J$51) | D10: =SUMPRODUCT((MONTH('Budget Planning'!$H$2:$H$51)=5)*(YEAR('Budget Planning'!$H$2:$H$51)=2025)*'Budget Planning'!$N$2:$N$51) | E10: =SUMPRODUCT((MONTH('Budget Planning'!$H$2:$H$51)=5)*(YEAR('Budget Planning'!$H$2:$H$51)=2025)*'Budget Planning'!$O$2:$O$51) | F10: =SUMPRODUCT((MONTH('Budget Planning'!$H$2:$H$51)=5)*(YEAR('Budget Planning'!$H$2:$H$51)=2025)*'Budget Planning'!$M$2:$M$51) | G10: =C10-F10 | H10: =IF(C10=0,0,G10/C10) | I10: =IF(C10=0,0,D10/C10) | J10: =IF(H10<-0.05,"At Risk","On Track")
A11: Jun | B11: =SUMPRODUCT((MONTH('Budget Planning'!$H$2:$H$51)=6)*(YEAR('Budget Planning'!$H$2:$H$51)=2025)*1) | C11: =SUMPRODUCT((MONTH('Budget Planning'!$H$2:$H$51)=6)*(YEAR('Budget Planning'!$H$2:$H$51)=2025)*'Budget Planning'!$J$2:$J$51) | D11: =SUMPRODUCT((MONTH('Budget Planning'!$H$2:$H$51)=6)*(YEAR('Budget Planning'!$H$2:$H$51)=2025)*'Budget Planning'!$N$2:$N$51) | E11: =SUMPRODUCT((MONTH('Budget Planning'!$H$2:$H$51)=6)*(YEAR('Budget Planning'!$H$2:$H$51)=2025)*'Budget Planning'!$O$2:$O$51) | F11: =SUMPRODUCT((MONTH('Budget Planning'!$H$2:$H$51)=6)*(YEAR('Budget Planning'!$H$2:$H$51)=2025)*'Budget Planning'!$M$2:$M$51) | G11: =C11-F11 | H11: =IF(C11=0,0,G11/C11) | I11: =IF(C11=0,0,D11/C11) | J11: =IF(H11<-0.05,"At Risk","On Track")
A12: Jul | B12: =SUMPRODUCT((MONTH('Budget Planning'!$H$2:$H$51)=7)*(YEAR('Budget Planning'!$H$2:$H$51)=2025)*1) | C12: =SUMPRODUCT((MONTH('Budget Planning'!$H$2:$H$51)=7)*(YEAR('Budget Planning'!$H$2:$H$51)=2025)*'Budget Planning'!$J$2:$J$51) | D12: =SUMPRODUCT((MONTH('Budget Planning'!$H$2:$H$51)=7)*(YEAR('Budget Planning'!$H$2:$H$51)=2025)*'Budget Planning'!$N$2:$N$51) | E12: =SUMPRODUCT((MONTH('Budget Planning'!$H$2:$H$51)=7)*(YEAR('Budget Planning'!$H$2:$H$51)=2025)*'Budget Planning'!$O$2:$O$51) | F12: =SUMPRODUCT((MONTH('Budget Planning'!$H$2:$H$51)=7)*(YEAR('Budget Planning'!$H$2:$H$51)=2025)*'Budget Planning'!$M$2:$M$51) | G12: =C12-F12 | H12: =IF(C12=0,0,G12/C12) | I12: =IF(C12=0,0,D12/C12) | J12: =IF(H12<-0.05,"At Risk","On Track")
A13: Aug | B13: =SUMPRODUCT((MONTH('Budget Planning'!$H$2:$H$51)=8)*(YEAR('Budget Planning'!$H$2:$H$51)=2025)*1) | C13: =SUMPRODUCT((MONTH('Budget Planning'!$H$2:$H$51)=8)*(YEAR('Budget Planning'!$H$2:$H$51)=2025)*'Budget Planning'!$J$2:$J$51) | D13: =SUMPRODUCT((MONTH('Budget Planning'!$H$2:$H$51)=8)*(YEAR('Budget Planning'!$H$2:$H$51)=2025)*'Budget Planning'!$N$2:$N$51) | E13: =SUMPRODUCT((MONTH('Budget Planning'!$H$2:$H$51)=8)*(YEAR('Budget Planning'!$H$2:$H$51)=2025)*'Budget Planning'!$O$2:$O$51) | F13: =SUMPRODUCT((MONTH('Budget Planning'!$H$2:$H$51)=8)*(YEAR('Budget Planning'!$H$2:$H$51)=2025)*'Budget Planning'!$M$2:$M$51) | G13: =C13-F13 | H13: =IF(C13=0,0,G13/C13) | I13: =IF(C13=0,0,D13/C13) | J13: =IF(H13<-0.05,"At Risk","On Track")
A14: Sep | B14: =SUMPRODUCT((MONTH('Budget Planning'!$H$2:$H$51)=9)*(YEAR('Budget Planning'!$H$2:$H$51)=2025)*1) | C14: =SUMPRODUCT((MONTH('Budget Planning'!$H$2:$H$51)=9)*(YEAR('Budget Planning'!$H$2:$H$51)=2025)*'Budget Planning'!$J$2:$J$51) | D14: =SUMPRODUCT((MONTH('Budget Planning'!$H$2:$H$51)=9)*(YEAR('Budget Planning'!$H$2:$H$51)=2025)*'Budget Planning'!$N$2:$N$51) | E14: =SUMPRODUCT((MONTH('Budget Planning'!$H$2:$H$51)=9)*(YEAR('Budget Planning'!$H$2:$H$51)=2025)*'Budget Planning'!$O$2:$O$51) | F14: =SUMPRODUCT((MONTH('Budget Planning'!$H$2:$H$51)=9)*(YEAR('Budget Planning'!$H$2:$H$51)=2025)*'Budget Planning'!$M$2:$M$51) | G14: =C14-F14 | H14: =IF(C14=0,0,G14/C14) | I14: =IF(C14=0,0,D14/C14) | J14: =IF(H14<-0.05,"At Risk","On Track")
A15: Oct | B15: =SUMPRODUCT((MONTH('Budget Planning'!$H$2:$H$51)=10)*(YEAR('Budget Planning'!$H$2:$H$51)=2025)*1) | C15: =SUMPRODUCT((MONTH('Budget Planning'!$H$2:$H$51)=10)*(YEAR('Budget Planning'!$H$2:$H$51)=2025)*'Budget Planning'!$J$2:$J$51) | D15: =SUMPRODUCT((MONTH('Budget Planning'!$H$2:$H$51)=10)*(YEAR('Budget Planning'!$H$2:$H$51)=2025)*'Budget Planning'!$N$2:$N$51) | E15: =SUMPRODUCT((MONTH('Budget Planning'!$H$2:$H$51)=10)*(YEAR('Budget Planning'!$H$2:$H$51)=2025)*'Budget Planning'!$O$2:$O$51) | F15: =SUMPRODUCT((MONTH('Budget Planning'!$H$2:$H$51)=10)*(YEAR('Budget Planning'!$H$2:$H$51)=2025)*'Budget Planning'!$M$2:$M$51) | G15: =C15-F15 | H15: =IF(C15=0,0,G15/C15) | I15: =IF(C15=0,0,D15/C15) | J15: =IF(H15<-0.05,"At Risk","On Track")
A16: Nov | B16: =SUMPRODUCT((MONTH('Budget Planning'!$H$2:$H$51)=11)*(YEAR('Budget Planning'!$H$2:$H$51)=2025)*1) | C16: =SUMPRODUCT((MONTH('Budget Planning'!$H$2:$H$51)=11)*(YEAR('Budget Planning'!$H$2:$H$51)=2025)*'Budget Planning'!$J$2:$J$51) | D16: =SUMPRODUCT((MONTH('Budget Planning'!$H$2:$H$51)=11)*(YEAR('Budget Planning'!$H$2:$H$51)=2025)*'Budget Planning'!$N$2:$N$51) | E16: =SUMPRODUCT((MONTH('Budget Planning'!$H$2:$H$51)=11)*(YEAR('Budget Planning'!$H$2:$H$51)=2025)*'Budget Planning'!$O$2:$O$51) | F16: =SUMPRODUCT((MONTH('Budget Planning'!$H$2:$H$51)=11)*(YEAR('Budget Planning'!$H$2:$H$51)=2025)*'Budget Planning'!$M$2:$M$51) | G16: =C16-F16 | H16: =IF(C16=0,0,G16/C16) | I16: =IF(C16=0,0,D16/C16) | J16: =IF(H16<-0.05,"At Risk","On Track")
A17: Dec | B17: =SUMPRODUCT((MONTH('Budget Planning'!$H$2:$H$51)=12)*(YEAR('Budget Planning'!$H$2:$H$51)=2025)*1) | C17: =SUMPRODUCT((MONTH('Budget Planning'!$H$2:$H$51)=12)*(YEAR('Budget Planning'!$H$2:$H$51)=2025)*'Budget Planning'!$J$2:$J$51) | D17: =SUMPRODUCT((MONTH('Budget Planning'!$H$2:$H$51)=12)*(YEAR('Budget Planning'!$H$2:$H$51)=2025)*'Budget Planning'!$N$2:$N$51) | E17: =SUMPRODUCT((MONTH('Budget Planning'!$H$2:$H$51)=12)*(YEAR('Budget Planning'!$H$2:$H$51)=2025)*'Budget Planning'!$O$2:$O$51) | F17: =SUMPRODUCT((MONTH('Budget Planning'!$H$2:$H$51)=12)*(YEAR('Budget Planning'!$H$2:$H$51)=2025)*'Budget Planning'!$M$2:$M$51) | G17: =C17-F17 | H17: =IF(C17=0,0,G17/C17) | I17: =IF(C17=0,0,D17/C17) | J17: =IF(H17<-0.05,"At Risk","On Track")
A18: FULL YEAR TOTAL | C18: =SUM(C6:C17) | D18: =SUM(D6:D17) | E18: =SUM(E6:E17) | F18: =SUM(F6:F17) | G18: =SUM(G6:G17) | H18: =IF(C18=0,0,G18/C18) | I18: =IF(C18=0,0,D18/C18)
A21: 2. QUARTERLY FINANCIAL SUMMARY
A22: Quarter | B22: # Events | C22: Budget (€) | D22: Committed (€) | E22: Actual (€) | F22: Forecast (€) | G22: Variance (€) | H22: Var % | I22: Forecast Accuracy % | J22: Status
A23: Q1 2025 | B23: =SUM(B6:B8) | C23: =SUM(C6:C8) | D23: =SUM(D6:D8) | E23: =SUM(E6:E8) | F23: =SUM(F6:F8) | G23: =C23-F23 | H23: =IF(C23=0,0,G23/C23) | I23: =1-ABS(H23) | J23: =IF(H23<-0.05,"At Risk","On Track")
A24: Q2 2025 | B24: =SUM(B9:B11) | C24: =SUM(C9:C11) | D24: =SUM(D9:D11) | E24: =SUM(E9:E11) | F24: =SUM(F9:F11) | G24: =C24-F24 | H24: =IF(C24=0,0,G24/C24) | I24: =1-ABS(H24) | J24: =IF(H24<-0.05,"At Risk","On Track")
A25: Q3 2025 | B25: =SUM(B12:B14) | C25: =SUM(C12:C14) | D25: =SUM(D12:D14) | E25: =SUM(E12:E14) | F25: =SUM(F12:F14) | G25: =C25-F25 | H25: =IF(C25=0,0,G25/C25) | I25: =1-ABS(H25) | J25: =IF(H25<-0.05,"At Risk","On Track")
A26: Q4 2025 | B26: =SUM(B15:B17) | C26: =SUM(C15:C17) | D26: =SUM(D15:D17) | E26: =SUM(E15:E17) | F26: =SUM(F15:F17) | G26: =C26-F26 | H26: =IF(C26=0,0,G26/C26) | I26: =1-ABS(H26) | J26: =IF(H26<-0.05,"At Risk","On Track")
A29: 3. BUDGET VS ACTUAL BY BUSINESS UNIT
A30: Business Unit | B30: # Events | C30: Budget (€) | D30: Committed (€) | E30: Actual (€) | F30: Forecast (€) | G30: Variance (€) | H30: Var % | I30: Absorption %
A31: BU Cardiovascular | B31: =COUNTIF('Budget Planning'!$F$2:$F$51,$A31) | C31: =SUMIF('Budget Planning'!$F$2:$F$51,$A31,'Budget Planning'!$J$2:$J$51) | D31: =SUMIF('Budget Planning'!$F$2:$F$51,$A31,'Budget Planning'!$N$2:$N$51) | E31: =SUMIF('Budget Planning'!$F$2:$F$51,$A31,'Budget Planning'!$O$2:$O$51) | F31: =SUMIF('Budget Planning'!$F$2:$F$51,$A31,'Budget Planning'!$M$2:$M$51) | G31: =C31-F31 | H31: =IF(C31=0,0,G31/C31) | I31: =IF(C31=0,0,D31/C31)
A32: BU Immunology | B32: =COUNTIF('Budget Planning'!$F$2:$F$51,$A32) | C32: =SUMIF('Budget Planning'!$F$2:$F$51,$A32,'Budget Planning'!$J$2:$J$51) | D32: =SUMIF('Budget Planning'!$F$2:$F$51,$A32,'Budget Planning'!$N$2:$N$51) | E32: =SUMIF('Budget Planning'!$F$2:$F$51,$A32,'Budget Planning'!$O$2:$O$51) | F32: =SUMIF('Budget Planning'!$F$2:$F$51,$A32,'Budget Planning'!$M$2:$M$51) | G32: =C32-F32 | H32: =IF(C32=0,0,G32/C32) | I32: =IF(C32=0,0,D32/C32)
A33: BU Infectious Diseases | B33: =COUNTIF('Budget Planning'!$F$2:$F$51,$A33) | C33: =SUMIF('Budget Planning'!$F$2:$F$51,$A33,'Budget Planning'!$J$2:$J$51) | D33: =SUMIF('Budget Planning'!$F$2:$F$51,$A33,'Budget Planning'!$N$2:$N$51) | E33: =SUMIF('Budget Planning'!$F$2:$F$51,$A33,'Budget Planning'!$O$2:$O$51) | F33: =SUMIF('Budget Planning'!$F$2:$F$51,$A33,'Budget Planning'!$M$2:$M$51) | G33: =C33-F33 | H33: =IF(C33=0,0,G33/C33) | I33: =IF(C33=0,0,D33/C33)
A34: BU Neuroscience | B34: =COUNTIF('Budget Planning'!$F$2:$F$51,$A34) | C34: =SUMIF('Budget Planning'!$F$2:$F$51,$A34,'Budget Planning'!$J$2:$J$51) | D34: =SUMIF('Budget Planning'!$F$2:$F$51,$A34,'Budget Planning'!$N$2:$N$51) | E34: =SUMIF('Budget Planning'!$F$2:$F$51,$A34,'Budget Planning'!$O$2:$O$51) | F34: =SUMIF('Budget Planning'!$F$2:$F$51,$A34,'Budget Planning'!$M$2:$M$51) | G34: =C34-F34 | H34: =IF(C34=0,0,G34/C34) | I34: =IF(C34=0,0,D34/C34)
A35: BU Oncology | B35: =COUNTIF('Budget Planning'!$F$2:$F$51,$A35) | C35: =SUMIF('Budget Planning'!$F$2:$F$51,$A35,'Budget Planning'!$J$2:$J$51) | D35: =SUMIF('Budget Planning'!$F$2:$F$51,$A35,'Budget Planning'!$N$2:$N$51) | E35: =SUMIF('Budget Planning'!$F$2:$F$51,$A35,'Budget Planning'!$O$2:$O$51) | F35: =SUMIF('Budget Planning'!$F$2:$F$51,$A35,'Budget Planning'!$M$2:$M$51) | G35: =C35-F35 | H35: =IF(C35=0,0,G35/C35) | I35: =IF(C35=0,0,D35/C35)
A36: BU Rare Diseases | B36: =COUNTIF('Budget Planning'!$F$2:$F$51,$A36) | C36: =SUMIF('Budget Planning'!$F$2:$F$51,$A36,'Budget Planning'!$J$2:$J$51) | D36: =SUMIF('Budget Planning'!$F$2:$F$51,$A36,'Budget Planning'!$N$2:$N$51) | E36: =SUMIF('Budget Planning'!$F$2:$F$51,$A36,'Budget Planning'!$O$2:$O$51) | F36: =SUMIF('Budget Planning'!$F$2:$F$51,$A36,'Budget Planning'!$M$2:$M$51) | G36: =C36-F36 | H36: =IF(C36=0,0,G36/C36) | I36: =IF(C36=0,0,D36/C36)

Sheet Documentation
A1: PHARMACEUTICAL EVENTS OPERATIONS – WORKBOOK DOCUMENTATION
A2: Version 1.1 | Created: 24 June 2026 | Owner: Finance & PMO | Classification: CONFIDENTIAL
A4: 1. WORKBOOK OVERVIEW
A5: Sheet Name | B5: Purpose
A6: Dashboard Executive | B6: High-level KPI overview for C-suite and senior management. Shows budget vs forecast, event status, supplier risk, and monthly trends. | E6: Auto-calculated via live formulas from source sheets (SUM/SUMIF/COUNTIF/SUMPRODUCT). No manual editing; recalculates on open.
A7: Event Master Database | B7: Master registry of all pharmaceutical events. Central reference used by all other sheets via XLOOKUP/SUMIFS. Each event has a unique Event ID. | E7: Event ID format: EVT-YYYY-NNN. Mandatory for all downstream modules.
A8: Budget Planning | B8: Full budget lifecycle management including initial budget, approved budget, multiple forecast versions, committed spend, and actuals. | E8: Forecast versions tracked for audit. Remaining, Variance and Variance % are live formulas (auditable, recalculate automatically).
A9: Supplier Management | B9: End-to-end supplier governance: contract status, PO linkage, invoice tracking, payment status, risk classification, and overdue monitoring. | E9: Risk indicator drives dashboard supplier concentration analysis.
A10: Cost Control | B10: Granular cost tracking by event and cost category. Enables variance analysis at P&L line level (Airfare, Hotel, Venue, F&B, AV, Agency Fees, etc.). | E10: Variance, Variance %, Absorption %, Over/Under and Status are live formulas linked to budgeted vs committed.
A11: PO Tracking | B11: Purchase order lifecycle management from request to payment. Tracks approval cycle times, invoice matching, and overdue payments. | E11: PO Number is foreign key linking to Supplier Management.
A12: Executive Reporting | B12: Consolidated financial summaries by month, quarter, and business unit. Includes Budget vs Actual, Forecast Accuracy, and BU-level variance. | E12: Monthly, quarterly and BU summaries are live formulas referencing Budget Planning. Refresh on open.
A13: Documentation | B13: This sheet. Describes structure, data model, business rules, naming conventions, and automation integration points. | E13: Update when adding new fields or changing business rules.
A16: 2. DATA MODEL & KEY RELATIONSHIPS
A17: Relationship | B17: Description
A18: Event Master → Budget Planning | B18: Each event (Event ID) has exactly one budget record. Budget Planning references Event Master for event metadata. | E18: 1:1
A19: Event Master → Supplier Management | B19: Each event can have multiple suppliers. Supplier records reference Event ID. Enables multi-supplier-per-event tracking. | E19: 1:N
A20: Event Master → Cost Control | B20: Each event has cost records per cost category (up to 11 categories). Cost Control aggregates to Budget Planning totals. | E20: 1:N
A21: Supplier Management → PO Tracking | B21: Each supplier record generates one PO. PO Number is the linking key. Tracks full procurement lifecycle. | E21: 1:1
A22: Budget Planning → Executive Reporting | B22: Executive Reporting summarizes Budget Planning data by month, quarter, and business unit using SUMIFS formulas. | E22: N:1 (aggregation)
A25: 3. BUSINESS RULES & FINANCIAL CONTROLS
A26: Rule ID | B26: Rule Description
A27: BR-001 | B27: Event ID must be unique and follow format EVT-YYYY-NNN. It is the primary key across all modules. | E27: Data integrity
A28: BR-002 | B28: Approved Budget cannot be changed after sign-off. Changes require a new Forecast Version (FV1, FV2, FV3). | E28: Audit / Governance
A29: BR-003 | B29: Current Forecast is always the latest Forecast Version. Never overwrite prior versions. | E29: Version control
A30: BR-004 | B30: Committed spend = sum of all signed POs. Actual spend = sum of all paid/invoiced amounts. | E30: Financial accuracy
A31: BR-005 | B31: Variance % alert threshold: >5% favorable = On Track; 5-15% adverse = At Risk; >15% adverse = Over Budget. | E31: Escalation triggers
A32: BR-006 | B32: Supplier Risk: High = contract not signed OR overdue payment OR disputed invoice. Medium = pending contract. Low = all clear. | E32: Risk management
A33: BR-007 | B33: PO must be approved before services are rendered. POs without approval dates are flagged in Cost Control. | E33: Compliance
A34: BR-008 | B34: All amounts in EUR. Foreign currency conversion at month-end rate logged in Notes field. | E34: Currency control
A35: BR-009 | B35: Status progression: Planning → Confirmed → In Progress → Completed → Closed. Cancellation can occur at any stage. | E35: Process governance
A36: BR-010 | B36: Overdue invoices are automatically flagged when Payment Status = Overdue AND Due Date < Today. | E36: Cash flow control
A39: 4. NAMING CONVENTIONS & COLUMN STANDARDS
A40: Convention | B40: Standard
A41: Table Names | B41: tblEvents, tblBudgets, tblSuppliers, tblCosts, tblPOs. Prefix 'tbl' + CamelCase. | E41: Power Query / Office Scripts compatibility
A42: Column Names | B42: PascalCase, no spaces, no special chars. E.g.: EventID, ApprovedBudget, PaymentStatus. | E42: Power Automate / SharePoint schema alignment
A43: Date Fields | B43: ISO format in data layer (YYYY-MM-DD). Display format DD/MM/YYYY via cell formatting. | E43: International standards
A44: Currency Fields | B44: EUR suffix in column headers. Numeric value only in cells. Format via number format string. | E44: Multi-currency readiness
A45: Percentage Fields | B45: Stored as decimal (0.15 = 15%). Display via percentage number format. | E45: Formula compatibility
A46: ID Fields | B46: EVT-YYYY-NNN (events), PO-YYYY-NNNN (POs), SUP-NNNN (suppliers), CC-NNNNN (cost lines). | E46: Traceability
A47: Status Fields | B47: Controlled via Data Validation dropdown lists. Closed list—no free text. | E47: Data quality
A48: Audit Fields | B48: CreatedDate, LastModified, RequestedBy, ApprovedBy on all transactional tables. | E48: SOX / audit trail
A51: 5. AUTOMATION INTEGRATION GUIDE
A52: System | B52: Integration Description
A53: Power Automate | B53: Connect to SharePoint document library. Trigger: on file modify. Action: refresh Power Query connections, send email alerts for Overdue invoices and High Risk suppliers. | E53: Active
A54: SharePoint Storage | B54: Store workbook in SharePoint Online. Enable co-authoring. Set version history to 500 versions. Use document library metadata for TA and BU tagging. | E54: Ready
A55: Office Scripts | B55: Script 1: Auto-populate Event ID on new row. Script 2: Set LastModified timestamp. Script 3: Flag overdue invoices. Script 4: Export Dashboard to PDF for distribution. | E55: Designed
A56: Power Query | B56: All structured tables (tblEvents, tblBudgets, etc.) are Power Query ready. Refresh all connections after data imports. Use Table.TransformColumnTypes for data type enforcement. | E56: Ready
A57: Power BI | B57: Connect Power BI Desktop to this workbook via Excel connector. Publish to Power BI Service for interactive executive dashboards with drill-through capability. | E57: Planned
A58: Teams Integration | B58: Use Power Automate to post weekly KPI summary card to Teams channel. Include Budget vs Forecast, Active Events count, and High Risk Supplier count. | E58: Planned
